Workbook

Sheet Summary Deshboard
A1: Dashboard Structure | D1: ME-wise Summary | J1: Product Type Summary
A2: Total Customers | B2: =COUNTA('Master sheet'!C:C)-1 -> 578 | D2: =IFERROR(__xludf.DUMMYFUNCTION("QUERY('Master sheet'!A:H,""select H,count(H) where H is not null group by H label count(H) 'Customers Onboarded'"",1)"),"Name of ME Who Onboarded") -> Name of ME Who Onboarded | E2: =IFERROR(__xludf.DUMMYFUNCTION("""COMPUTED_VALUE"""),"Customers Onboarded") -> Customers Onboarded | J2: =IFERROR(__xludf.DUMMYFUNCTION("QUERY('Master sheet'!A:H,""select F,count(F) where F is not null group by F"",1)"),"Product Type") -> Product Type | K2: =IFERROR(__xludf.DUMMYFUNCTION("""COMPUTED_VALUE"""),"count Product Type") -> count Product Type
D3: =IFERROR(__xludf.DUMMYFUNCTION("""COMPUTED_VALUE"""),"Abhishek Malviye") -> Abhishek Malviye | E3: =IFERROR(__xludf.DUMMYFUNCTION("""COMPUTED_VALUE"""),5) -> 5 | J3: =IFERROR(__xludf.DUMMYFUNCTION("""COMPUTED_VALUE"""),"ADVANCED CUSTOMER") -> ADVANCED CUSTOMER | K3: =IFERROR(__xludf.DUMMYFUNCTION("""COMPUTED_VALUE"""),72) -> 72
A4: Total B2B | B4: =COUNTIF('Master sheet'!G:G,"B2B") -> 3 | D4: =IFERROR(__xludf.DUMMYFUNCTION("""COMPUTED_VALUE"""),"Anil kumar kayasth") -> Anil kumar kayasth | E4: =IFERROR(__xludf.DUMMYFUNCTION("""COMPUTED_VALUE"""),11) -> 11 | J4: =IFERROR(__xludf.DUMMYFUNCTION("""COMPUTED_VALUE"""),"BNPL") -> BNPL | K4: =IFERROR(__xludf.DUMMYFUNCTION("""COMPUTED_VALUE"""),2) -> 2
D5: =IFERROR(__xludf.DUMMYFUNCTION("""COMPUTED_VALUE"""),"Ashok Jatiya") -> Ashok Jatiya | E5: =IFERROR(__xludf.DUMMYFUNCTION("""COMPUTED_VALUE"""),1) -> 1 | J5: =IFERROR(__xludf.DUMMYFUNCTION("""COMPUTED_VALUE"""),"BNPL SPEED ") -> BNPL SPEED | K5: =IFERROR(__xludf.DUMMYFUNCTION("""COMPUTED_VALUE"""),1) -> 1
A6: Total B2C | B6: =COUNTIF('Master sheet'!G:G,"B2C") -> 575 | D6: =IFERROR(__xludf.DUMMYFUNCTION("""COMPUTED_VALUE"""),"Ayush Gupta") -> Ayush Gupta | E6: =IFERROR(__xludf.DUMMYFUNCTION("""COMPUTED_VALUE"""),5) -> 5 | J6: =IFERROR(__xludf.DUMMYFUNCTION("""COMPUTED_VALUE"""),"BNPL SPEED POST") -> BNPL SPEED POST | K6: =IFERROR(__xludf.DUMMYFUNCTION("""COMPUTED_VALUE"""),1) -> 1
D7: =IFERROR(__xludf.DUMMYFUNCTION("""COMPUTED_VALUE"""),"BRIJESH SHRIVAS") -> BRIJESH SHRIVAS | E7: =IFERROR(__xludf.DUMMYFUNCTION("""COMPUTED_VALUE"""),9) -> 9 | J7: =IFERROR(__xludf.DUMMYFUNCTION("""COMPUTED_VALUE"""),"BNPL speed post") -> BNPL speed post | K7: =IFERROR(__xludf.DUMMYFUNCTION("""COMPUTED_VALUE"""),2) -> 2
A8: Today's Onboarding | B8: =COUNTIF('Master sheet'!E:E,TODAY()) -> 0 | D8: =IFERROR(__xludf.DUMMYFUNCTION("""COMPUTED_VALUE"""),"DEEPIKA VERMA") -> DEEPIKA VERMA | E8: =IFERROR(__xludf.DUMMYFUNCTION("""COMPUTED_VALUE"""),2) -> 2 | J8: =IFERROR(__xludf.DUMMYFUNCTION("""COMPUTED_VALUE"""),"FASHION ") -> FASHION | K8: =IFERROR(__xludf.DUMMYFUNCTION("""COMPUTED_VALUE"""),1) -> 1
D9: =IFERROR(__xludf.DUMMYFUNCTION("""COMPUTED_VALUE"""),"DURGA SHANKAR GARASIYA") -> DURGA SHANKAR GARASIYA | E9: =IFERROR(__xludf.DUMMYFUNCTION("""COMPUTED_VALUE"""),17) -> 17 | J9: =IFERROR(__xludf.DUMMYFUNCTION("""COMPUTED_VALUE"""),"FMCG") -> FMCG | K9: =IFERROR(__xludf.DUMMYFUNCTION("""COMPUTED_VALUE"""),1) -> 1
A10: This Month Onboarding | B10: =COUNTIFS('Master sheet'!E:E,">="&EOMONTH(TODAY(),-1)+1,'Master sheet'!E:E,"<="&EOMONTH(TODAY(),0)) -> 0 | D10: =IFERROR(__xludf.DUMMYFUNCTION("""COMPUTED_VALUE"""),"HARSHIT PARMAR") -> HARSHIT PARMAR | E10: =IFERROR(__xludf.DUMMYFUNCTION("""COMPUTED_VALUE"""),6) -> 6 | J10: =IFERROR(__xludf.DUMMYFUNCTION("""COMPUTED_VALUE"""),"HERBVAL PRODUCTS") -> HERBVAL PRODUCTS | K10: =IFERROR(__xludf.DUMMYFUNCTION("""COMPUTED_VALUE"""),2) -> 2
D11: =IFERROR(__xludf.DUMMYFUNCTION("""COMPUTED_VALUE"""),"HEMANT BAGHEL") -> HEMANT BAGHEL | E11: =IFERROR(__xludf.DUMMYFUNCTION("""COMPUTED_VALUE"""),4) -> 4 | J11: =IFERROR(__xludf.DUMMYFUNCTION("""COMPUTED_VALUE"""),"INDIA POST PARCEL CONTRACTUAL ") -> INDIA POST PARCEL CONTRACTUAL | K11: =IFERROR(__xludf.DUMMYFUNCTION("""COMPUTED_VALUE"""),2) -> 2
D12: =IFERROR(__xludf.DUMMYFUNCTION("""COMPUTED_VALUE"""),"HIMMAT SINGH") -> HIMMAT SINGH | E12: =IFERROR(__xludf.DUMMYFUNCTION("""COMPUTED_VALUE"""),22) -> 22 | J12: =IFERROR(__xludf.DUMMYFUNCTION("""COMPUTED_VALUE"""),"INDIAPOST PARCEL CONTRACTUAL") -> INDIAPOST PARCEL CONTRACTUAL | K12: =IFERROR(__xludf.DUMMYFUNCTION("""COMPUTED_VALUE"""),2) -> 2
D13: =IFERROR(__xludf.DUMMYFUNCTION("""COMPUTED_VALUE"""),"JUNAId khan") -> JUNAId khan | E13: =IFERROR(__xludf.DUMMYFUNCTION("""COMPUTED_VALUE"""),1) -> 1 | J13: =IFERROR(__xludf.DUMMYFUNCTION("""COMPUTED_VALUE"""),"INDIAPOST PARCEL CONTRACTUAL ") -> INDIAPOST PARCEL CONTRACTUAL | K13: =IFERROR(__xludf.DUMMYFUNCTION("""COMPUTED_VALUE"""),3) -> 3
D14: =IFERROR(__xludf.DUMMYFUNCTION("""COMPUTED_VALUE"""),"Jalaj Rawat") -> Jalaj Rawat | E14: =IFERROR(__xludf.DUMMYFUNCTION("""COMPUTED_VALUE"""),71) -> 71 | J14: =IFERROR(__xludf.DUMMYFUNCTION("""COMPUTED_VALUE"""),"India Post Parcel Contractual") -> India Post Parcel Contractual | K14: =IFERROR(__xludf.DUMMYFUNCTION("""COMPUTED_VALUE"""),17) -> 17
D15: =IFERROR(__xludf.DUMMYFUNCTION("""COMPUTED_VALUE"""),"Kavita Bhuriya") -> Kavita Bhuriya | E15: =IFERROR(__xludf.DUMMYFUNCTION("""COMPUTED_VALUE"""),2) -> 2 | J15: =IFERROR(__xludf.DUMMYFUNCTION("""COMPUTED_VALUE"""),"Indiapost Parcel Contractual") -> Indiapost Parcel Contractual | K15: =IFERROR(__xludf.DUMMYFUNCTION("""COMPUTED_VALUE"""),45) -> 45
D16: =IFERROR(__xludf.DUMMYFUNCTION("""COMPUTED_VALUE"""),"Kunal Baurasi") -> Kunal Baurasi | E16: =IFERROR(__xludf.DUMMYFUNCTION("""COMPUTED_VALUE"""),4) -> 4 | J16: =IFERROR(__xludf.DUMMYFUNCTION("""COMPUTED_VALUE"""),"International EMS Document") -> International EMS Document | K16: =IFERROR(__xludf.DUMMYFUNCTION("""COMPUTED_VALUE"""),1) -> 1
D17: =IFERROR(__xludf.DUMMYFUNCTION("""COMPUTED_VALUE"""),"NEELESH VERMA") -> NEELESH VERMA | E17: =IFERROR(__xludf.DUMMYFUNCTION("""COMPUTED_VALUE"""),20) -> 20 | J17: =IFERROR(__xludf.DUMMYFUNCTION("""COMPUTED_VALUE"""),"International Tracked Packet Service") -> International Tracked Packet Service | K17: =IFERROR(__xludf.DUMMYFUNCTION("""COMPUTED_VALUE"""),1) -> 1
D18: =IFERROR(__xludf.DUMMYFUNCTION("""COMPUTED_VALUE"""),"Narendra Baviskar") -> Narendra Baviskar | E18: =IFERROR(__xludf.DUMMYFUNCTION("""COMPUTED_VALUE"""),52) -> 52 | J18: =IFERROR(__xludf.DUMMYFUNCTION("""COMPUTED_VALUE"""),"LETTERS") -> LETTERS | K18: =IFERROR(__xludf.DUMMYFUNCTION("""COMPUTED_VALUE"""),10) -> 10
D19: =IFERROR(__xludf.DUMMYFUNCTION("""COMPUTED_VALUE"""),"RAHUL AGRAWAL") -> RAHUL AGRAWAL | E19: =IFERROR(__xludf.DUMMYFUNCTION("""COMPUTED_VALUE"""),43) -> 43 | J19: =IFERROR(__xludf.DUMMYFUNCTION("""COMPUTED_VALUE"""),"LETTES") -> LETTES | K19: =IFERROR(__xludf.DUMMYFUNCTION("""COMPUTED_VALUE"""),1) -> 1
D20: =IFERROR(__xludf.DUMMYFUNCTION("""COMPUTED_VALUE"""),"RAJENDRA PUSHPAD") -> RAJENDRA PUSHPAD | E20: =IFERROR(__xludf.DUMMYFUNCTION("""COMPUTED_VALUE"""),7) -> 7 | J20: =IFERROR(__xludf.DUMMYFUNCTION("""COMPUTED_VALUE"""),"MACHINE GOODS") -> MACHINE GOODS | K20: =IFERROR(__xludf.DUMMYFUNCTION("""COMPUTED_VALUE"""),3) -> 3
D21: =IFERROR(__xludf.DUMMYFUNCTION("""COMPUTED_VALUE"""),"RISHABH SINGH GOUR") -> RISHABH SINGH GOUR | E21: =IFERROR(__xludf.DUMMYFUNCTION("""COMPUTED_VALUE"""),25) -> 25 | J21: =IFERROR(__xludf.DUMMYFUNCTION("""COMPUTED_VALUE"""),"MEDICINES") -> MEDICINES | K21: =IFERROR(__xludf.DUMMYFUNCTION("""COMPUTED_VALUE"""),1) -> 1
D22: =IFERROR(__xludf.DUMMYFUNCTION("""COMPUTED_VALUE"""),"Rahul Panchal") -> Rahul Panchal | E22: =IFERROR(__xludf.DUMMYFUNCTION("""COMPUTED_VALUE"""),37) -> 37 | J22: =IFERROR(__xludf.DUMMYFUNCTION("""COMPUTED_VALUE"""),"Magazine Post") -> Magazine Post | K22: =IFERROR(__xludf.DUMMYFUNCTION("""COMPUTED_VALUE"""),7) -> 7
D23: =IFERROR(__xludf.DUMMYFUNCTION("""COMPUTED_VALUE"""),"Rajendra pushpad") -> Rajendra pushpad | E23: =IFERROR(__xludf.DUMMYFUNCTION("""COMPUTED_VALUE"""),1) -> 1 | J23: =IFERROR(__xludf.DUMMYFUNCTION("""COMPUTED_VALUE"""),"PARCEL") -> PARCEL | K23: =IFERROR(__xludf.DUMMYFUNCTION("""COMPUTED_VALUE"""),5) -> 5
D24: =IFERROR(__xludf.DUMMYFUNCTION("""COMPUTED_VALUE"""),"SANTOSH RATHORE") -> SANTOSH RATHORE | E24: =IFERROR(__xludf.DUMMYFUNCTION("""COMPUTED_VALUE"""),4) -> 4 | J24: =IFERROR(__xludf.DUMMYFUNCTION("""COMPUTED_VALUE"""),"Registered Mails") -> Registered Mails | K24: =IFERROR(__xludf.DUMMYFUNCTION("""COMPUTED_VALUE"""),13) -> 13
D25: =IFERROR(__xludf.DUMMYFUNCTION("""COMPUTED_VALUE"""),"SANTOSH VERMA") -> SANTOSH VERMA | E25: =IFERROR(__xludf.DUMMYFUNCTION("""COMPUTED_VALUE"""),18) -> 18 | J25: =IFERROR(__xludf.DUMMYFUNCTION("""COMPUTED_VALUE"""),"SHOES") -> SHOES | K25: =IFERROR(__xludf.DUMMYFUNCTION("""COMPUTED_VALUE"""),1) -> 1
D26: =IFERROR(__xludf.DUMMYFUNCTION("""COMPUTED_VALUE"""),"Shri Vishal Soni") -> Shri Vishal Soni | E26: =IFERROR(__xludf.DUMMYFUNCTION("""COMPUTED_VALUE"""),40) -> 40 | J26: =IFERROR(__xludf.DUMMYFUNCTION("""COMPUTED_VALUE"""),"SPEED POST AND PARCEL CONTRACTUAL ") -> SPEED POST AND PARCEL CONTRACTUAL | K26: =IFERROR(__xludf.DUMMYFUNCTION("""COMPUTED_VALUE"""),1) -> 1
D27: =IFERROR(__xludf.DUMMYFUNCTION("""COMPUTED_VALUE"""),"Shri Yash Mittal") -> Shri Yash Mittal | E27: =IFERROR(__xludf.DUMMYFUNCTION("""COMPUTED_VALUE"""),52) -> 52 | J27: =IFERROR(__xludf.DUMMYFUNCTION("""COMPUTED_VALUE"""),"SPORTS PRODUCTS") -> SPORTS PRODUCTS | K27: =IFERROR(__xludf.DUMMYFUNCTION("""COMPUTED_VALUE"""),2) -> 2
D28: =IFERROR(__xludf.DUMMYFUNCTION("""COMPUTED_VALUE"""),"Sunil bhojwani") -> Sunil bhojwani | E28: =IFERROR(__xludf.DUMMYFUNCTION("""COMPUTED_VALUE"""),3) -> 3 | J28: =IFERROR(__xludf.DUMMYFUNCTION("""COMPUTED_VALUE"""),"Speed Post") -> Speed Post | K28: =IFERROR(__xludf.DUMMYFUNCTION("""COMPUTED_VALUE"""),29) -> 29
D29: =IFERROR(__xludf.DUMMYFUNCTION("""COMPUTED_VALUE"""),"Surendra Singh") -> Surendra Singh | E29: =IFERROR(__xludf.DUMMYFUNCTION("""COMPUTED_VALUE"""),4) -> 4 | J29: =IFERROR(__xludf.DUMMYFUNCTION("""COMPUTED_VALUE"""),"Speed Post Document") -> Speed Post Document | K29: =IFERROR(__xludf.DUMMYFUNCTION("""COMPUTED_VALUE"""),3) -> 3
D30: =IFERROR(__xludf.DUMMYFUNCTION("""COMPUTED_VALUE"""),"VINEET PATEL") -> VINEET PATEL | E30: =IFERROR(__xludf.DUMMYFUNCTION("""COMPUTED_VALUE"""),24) -> 24 | J30: =IFERROR(__xludf.DUMMYFUNCTION("""COMPUTED_VALUE"""),"Speed Post Parcel Contractual") -> Speed Post Parcel Contractual | K30: =IFERROR(__xludf.DUMMYFUNCTION("""COMPUTED_VALUE"""),1) -> 1
D31: =IFERROR(__xludf.DUMMYFUNCTION("""COMPUTED_VALUE"""),"Vineet Patel") -> Vineet Patel | E31: =IFERROR(__xludf.DUMMYFUNCTION("""COMPUTED_VALUE"""),2) -> 2 | J31: =IFERROR(__xludf.DUMMYFUNCTION("""COMPUTED_VALUE"""),"Speed Post Parcel Domestic") -> Speed Post Parcel Domestic | K31: =IFERROR(__xludf.DUMMYFUNCTION("""COMPUTED_VALUE"""),27) -> 27
D32: =IFERROR(__xludf.DUMMYFUNCTION("""COMPUTED_VALUE"""),"Zuber Ahmed Khan") -> Zuber Ahmed Khan | E32: =IFERROR(__xludf.DUMMYFUNCTION("""COMPUTED_VALUE"""),36) -> 36 | J32: =IFERROR(__xludf.DUMMYFUNCTION("""COMPUTED_VALUE"""),"Speed Post ParcelÂ Domestic") -> Speed Post ParcelÂ Domestic | K32: =IFERROR(__xludf.DUMMYFUNCTION("""COMPUTED_VALUE"""),2) -> 2
D33: =IFERROR(__xludf.DUMMYFUNCTION("""COMPUTED_VALUE"""),"junaid khan") -> junaid khan | E33: =IFERROR(__xludf.DUMMYFUNCTION("""COMPUTED_VALUE"""),13) -> 13 | J33: =IFERROR(__xludf.DUMMYFUNCTION("""COMPUTED_VALUE"""),"Speed Post,Indiapost Parcel Contractual") -> Speed Post,Indiapost Parcel Contractual | K33: =IFERROR(__xludf.DUMMYFUNCTION("""COMPUTED_VALUE"""),1) -> 1
D34: =IFERROR(__xludf.DUMMYFUNCTION("""COMPUTED_VALUE"""),"santosh rathore ") -> santosh rathore | E34: =IFERROR(__xludf.DUMMYFUNCTION("""COMPUTED_VALUE"""),2) -> 2 | J34: =IFERROR(__xludf.DUMMYFUNCTION("""COMPUTED_VALUE"""),"advance customer") -> advance customer | K34: =IFERROR(__xludf.DUMMYFUNCTION("""COMPUTED_VALUE"""),1) -> 1
D35: =IFERROR(__xludf.DUMMYFUNCTION("""COMPUTED_VALUE"""),"sunil bhojwani") -> sunil bhojwani | E35: =IFERROR(__xludf.DUMMYFUNCTION("""COMPUTED_VALUE"""),16) -> 16 | J35: =IFERROR(__xludf.DUMMYFUNCTION("""COMPUTED_VALUE"""),"bnpl-speed post") -> bnpl-speed post | K35: =IFERROR(__xludf.DUMMYFUNCTION("""COMPUTED_VALUE"""),10) -> 10
D36: =IFERROR(__xludf.DUMMYFUNCTION("""COMPUTED_VALUE"""),"vineet Patel ") -> vineet Patel | E36: =IFERROR(__xludf.DUMMYFUNCTION("""COMPUTED_VALUE"""),1) -> 1 | J36: =IFERROR(__xludf.DUMMYFUNCTION("""COMPUTED_VALUE"""),"parcel contractual") -> parcel contractual | K36: =IFERROR(__xludf.DUMMYFUNCTION("""COMPUTED_VALUE"""),1) -> 1
D37: =IFERROR(__xludf.DUMMYFUNCTION("""COMPUTED_VALUE"""),"vineet patel") -> vineet patel | E37: =IFERROR(__xludf.DUMMYFUNCTION("""COMPUTED_VALUE"""),3) -> 3 | J37: =IFERROR(__xludf.DUMMYFUNCTION("""COMPUTED_VALUE"""),"parcel contractual ") -> parcel contractual | K37: =IFERROR(__xludf.DUMMYFUNCTION("""COMPUTED_VALUE"""),4) -> 4
D38: =IFERROR(__xludf.DUMMYFUNCTION("""COMPUTED_VALUE"""),"vineet patel ") -> vineet patel | E38: =IFERROR(__xludf.DUMMYFUNCTION("""COMPUTED_VALUE"""),1) -> 1
A49: Division Summary
A50: =IFERROR(__xludf.DUMMYFUNCTION("QUERY('Master sheet'!A:H,""select B,count(B) where B is not null group by B"",1)"),"Division") -> Division | B50: =IFERROR(__xludf.DUMMYFUNCTION("""COMPUTED_VALUE"""),"count Division") -> count Division
A51: =IFERROR(__xludf.DUMMYFUNCTION("""COMPUTED_VALUE"""),"Indore City") -> Indore City | B51: =IFERROR(__xludf.DUMMYFUNCTION("""COMPUTED_VALUE"""),144) -> 144
A52: =IFERROR(__xludf.DUMMYFUNCTION("""COMPUTED_VALUE"""),"Indore MFL") -> Indore MFL | B52: =IFERROR(__xludf.DUMMYFUNCTION("""COMPUTED_VALUE"""),27) -> 27
A53: =IFERROR(__xludf.DUMMYFUNCTION("""COMPUTED_VALUE"""),"Khandwa") -> Khandwa | B53: =IFERROR(__xludf.DUMMYFUNCTION("""COMPUTED_VALUE"""),74) -> 74
A54: =IFERROR(__xludf.DUMMYFUNCTION("""COMPUTED_VALUE"""),"Mandsaur") -> Mandsaur | B54: =IFERROR(__xludf.DUMMYFUNCTION("""COMPUTED_VALUE"""),102) -> 102
A55: =IFERROR(__xludf.DUMMYFUNCTION("""COMPUTED_VALUE"""),"RMS ID Dn") -> RMS ID Dn | B55: =IFERROR(__xludf.DUMMYFUNCTION("""COMPUTED_VALUE"""),52) -> 52
A56: =IFERROR(__xludf.DUMMYFUNCTION("""COMPUTED_VALUE"""),"Ratlam") -> Ratlam | B56: =IFERROR(__xludf.DUMMYFUNCTION("""COMPUTED_VALUE"""),25) -> 25
A57: =IFERROR(__xludf.DUMMYFUNCTION("""COMPUTED_VALUE"""),"Sehore") -> Sehore | B57: =IFERROR(__xludf.DUMMYFUNCTION("""COMPUTED_VALUE"""),56) -> 56
A58: =IFERROR(__xludf.DUMMYFUNCTION("""COMPUTED_VALUE"""),"Ujjain") -> Ujjain | B58: =IFERROR(__xludf.DUMMYFUNCTION("""COMPUTED_VALUE"""),102) -> 102

Sheet Master sheet
A1: S.No. | B1: Division | C1: Name of Customer | D1: Customer ID | E1: Date of Onboarding | F1: Product Type | G1: B2B Or B2C | H1: Name of ME Who Onboarded
A2: =IFERROR(__xludf.DUMMYFUNCTION("QUERY({'Indore City'!B4:I999;'Indore MFL'!B4:I999;Khandwa!B4:I1000;Mandsaur!B4:I1000;Ratlam!B4:I997;Sehore!B4:I1000;Ujjain!B4:I995;'RMS ID Dn'!B5:I972},""SELECT * WHERE Col1 IS NOT NULL"",0)"),1) -> 1 | B2: =IFERROR(__xludf.DUMMYFUNCTION("""COMPUTED_VALUE"""),"Indore City") -> Indore City | C2: =IFERROR(__xludf.DUMMYFUNCTION("""COMPUTED_VALUE"""),"DRASHTI ENTERPRISES") -> DRASHTI ENTERPRISES | D2: =IFERROR(__xludf.DUMMYFUNCTION("""COMPUTED_VALUE"""),1504860613) -> 1504860613 | E2: =IFERROR(__xludf.DUMMYFUNCTION("""COMPUTED_VALUE"""),46114) -> 46114 | G2: =IFERROR(__xludf.DUMMYFUNCTION("""COMPUTED_VALUE"""),"B2C") -> B2C | H2: =IFERROR(__xludf.DUMMYFUNCTION("""COMPUTED_VALUE"""),"Jalaj Rawat") -> Jalaj Rawat
A3: =IFERROR(__xludf.DUMMYFUNCTION("""COMPUTED_VALUE"""),2) -> 2 | B3: =IFERROR(__xludf.DUMMYFUNCTION("""COMPUTED_VALUE"""),"Indore City") -> Indore City | C3: =IFERROR(__xludf.DUMMYFUNCTION("""COMPUTED_VALUE"""),"PRIYAL AQUATECH SERVICES") -> PRIYAL AQUATECH SERVICES | D3: =IFERROR(__xludf.DUMMYFUNCTION("""COMPUTED_VALUE"""),1893026504) -> 1893026504 | E3: =IFERROR(__xludf.DUMMYFUNCTION("""COMPUTED_VALUE"""),46114) -> 46114 | G3: =IFERROR(__xludf.DUMMYFUNCTION("""COMPUTED_VALUE"""),"B2C") -> B2C | H3: =IFERROR(__xludf.DUMMYFUNCTION("""COMPUTED_VALUE"""),"Jalaj Rawat") -> Jalaj Rawat
A4: =IFERROR(__xludf.DUMMYFUNCTION("""COMPUTED_VALUE"""),3) -> 3 | B4: =IFERROR(__xludf.DUMMYFUNCTION("""COMPUTED_VALUE"""),"Indore City") -> Indore City | C4: =IFERROR(__xludf.DUMMYFUNCTION("""COMPUTED_VALUE"""),"VARNSHIKA HERBALS PVT LTD") -> VARNSHIKA HERBALS PVT LTD | D4: =IFERROR(__xludf.DUMMYFUNCTION("""COMPUTED_VALUE"""),1149636129) -> 1149636129 | E4: =IFERROR(__xludf.DUMMYFUNCTION("""COMPUTED_VALUE"""),46114) -> 46114 | G4: =IFERROR(__xludf.DUMMYFUNCTION("""COMPUTED_VALUE"""),"B2C") -> B2C | H4: =IFERROR(__xludf.DUMMYFUNCTION("""COMPUTED_VALUE"""),"Rahul Panchal") -> Rahul Panchal
A5: =IFERROR(__xludf.DUMMYFUNCTION("""COMPUTED_VALUE"""),4) -> 4 | B5: =IFERROR(__xludf.DUMMYFUNCTION("""COMPUTED_VALUE"""),"Indore City") -> Indore City | C5: =IFERROR(__xludf.DUMMYFUNCTION("""COMPUTED_VALUE"""),"SANWARIYA HERBALS") -> SANWARIYA HERBALS | D5: =IFERROR(__xludf.DUMMYFUNCTION("""COMPUTED_VALUE"""),1858516980) -> 1858516980 | E5: =IFERROR(__xludf.DUMMYFUNCTION("""COMPUTED_VALUE"""),46119) -> 46119 | G5: =IFERROR(__xludf.DUMMYFUNCTION("""COMPUTED_VALUE"""),"B2C") -> B2C | H5: =IFERROR(__xludf.DUMMYFUNCTION("""COMPUTED_VALUE"""),"Jalaj Rawat") -> Jalaj Rawat
A6: =IFERROR(__xludf.DUMMYFUNCTION("""COMPUTED_VALUE"""),5) -> 5 | B6: =IFERROR(__xludf.DUMMYFUNCTION("""COMPUTED_VALUE"""),"Indore City") -> Indore City | C6: =IFERROR(__xludf.DUMMYFUNCTION("""COMPUTED_VALUE"""),"Bank of India zonal office indore") -> Bank of India zonal office indore | D6: =IFERROR(__xludf.DUMMYFUNCTION("""COMPUTED_VALUE"""),1540291063) -> 1540291063 | E6: =IFERROR(__xludf.DUMMYFUNCTION("""COMPUTED_VALUE"""),46121) -> 46121 | G6: =IFERROR(__xludf.DUMMYFUNCTION("""COMPUTED_VALUE"""),"B2C") -> B2C | H6: =IFERROR(__xludf.DUMMYFUNCTION("""COMPUTED_VALUE"""),"Jalaj Rawat") -> Jalaj Rawat
A7: =IFERROR(__xludf.DUMMYFUNCTION("""COMPUTED_VALUE"""),6) -> 6 | B7: =IFERROR(__xludf.DUMMYFUNCTION("""COMPUTED_VALUE"""),"Indore City") -> Indore City | C7: =IFERROR(__xludf.DUMMYFUNCTION("""COMPUTED_VALUE"""),"SWARAJ COACHING CLASSES") -> SWARAJ COACHING CLASSES | D7: =IFERROR(__xludf.DUMMYFUNCTION("""COMPUTED_VALUE"""),1601260495) -> 1601260495 | E7: =IFERROR(__xludf.DUMMYFUNCTION("""COMPUTED_VALUE"""),46121) -> 46121 | G7: =IFERROR(__xludf.DUMMYFUNCTION("""COMPUTED_VALUE"""),"B2C") -> B2C | H7: =IFERROR(__xludf.DUMMYFUNCTION("""COMPUTED_VALUE"""),"Zuber Ahmed Khan") -> Zuber Ahmed Khan
A8: =IFERROR(__xludf.DUMMYFUNCTION("""COMPUTED_VALUE"""),7) -> 7 | B8: =IFERROR(__xludf.DUMMYFUNCTION("""COMPUTED_VALUE"""),"Indore City") -> Indore City | C8: =IFERROR(__xludf.DUMMYFUNCTION("""COMPUTED_VALUE"""),"MPPKVVCL") -> MPPKVVCL | D8: =IFERROR(__xludf.DUMMYFUNCTION("""COMPUTED_VALUE"""),1955152285) -> 1955152285 | E8: =IFERROR(__xludf.DUMMYFUNCTION("""COMPUTED_VALUE"""),46127) -> 46127 | G8: =IFERROR(__xludf.DUMMYFUNCTION("""COMPUTED_VALUE"""),"B2C") -> B2C | H8: =IFERROR(__xludf.DUMMYFUNCTION("""COMPUTED_VALUE"""),"Rahul Panchal") -> Rahul Panchal
A9: =IFERROR(__xludf.DUMMYFUNCTION("""COMPUTED_VALUE"""),8) -> 8 | B9: =IFERROR(__xludf.DUMMYFUNCTION("""COMPUTED_VALUE"""),"Indore City") -> Indore City | C9: =IFERROR(__xludf.DUMMYFUNCTION("""COMPUTED_VALUE"""),"RSP ENTERPRISES") -> RSP ENTERPRISES | D9: =IFERROR(__xludf.DUMMYFUNCTION("""COMPUTED_VALUE"""),1784698475) -> 1784698475 | E9: =IFERROR(__xludf.DUMMYFUNCTION("""COMPUTED_VALUE"""),46127) -> 46127 | G9: =IFERROR(__xludf.DUMMYFUNCTION("""COMPUTED_VALUE"""),"B2C") -> B2C | H9: =IFERROR(__xludf.DUMMYFUNCTION("""COMPUTED_VALUE"""),"Jalaj Rawat") -> Jalaj Rawat
A10: =IFERROR(__xludf.DUMMYFUNCTION("""COMPUTED_VALUE"""),9) -> 9 | B10: =IFERROR(__xludf.DUMMYFUNCTION("""COMPUTED_VALUE"""),"Indore City") -> Indore City | C10: =IFERROR(__xludf.DUMMYFUNCTION("""COMPUTED_VALUE"""),"SP WORLD SOLUTION") -> SP WORLD SOLUTION | D10: =IFERROR(__xludf.DUMMYFUNCTION("""COMPUTED_VALUE"""),1802814193) -> 1802814193 | E10: =IFERROR(__xludf.DUMMYFUNCTION("""COMPUTED_VALUE"""),46127) -> 46127 | G10: =IFERROR(__xludf.DUMMYFUNCTION("""COMPUTED_VALUE"""),"B2C") -> B2C | H10: =IFERROR(__xludf.DUMMYFUNCTION("""COMPUTED_VALUE"""),"Jalaj Rawat") -> Jalaj Rawat
A11: =IFERROR(__xludf.DUMMYFUNCTION("""COMPUTED_VALUE"""),10) -> 10 | B11: =IFERROR(__xludf.DUMMYFUNCTION("""COMPUTED_VALUE"""),"Indore City") -> Indore City | C11: =IFERROR(__xludf.DUMMYFUNCTION("""COMPUTED_VALUE"""),"ASHU HERBAL") -> ASHU HERBAL | D11: =IFERROR(__xludf.DUMMYFUNCTION("""COMPUTED_VALUE"""),1264378880) -> 1264378880 | E11: =IFERROR(__xludf.DUMMYFUNCTION("""COMPUTED_VALUE"""),46128) -> 46128 | G11: =IFERROR(__xludf.DUMMYFUNCTION("""COMPUTED_VALUE"""),"B2C") -> B2C | H11: =IFERROR(__xludf.DUMMYFUNCTION("""COMPUTED_VALUE"""),"Zuber Ahmed Khan") -> Zuber Ahmed Khan
A12: =IFERROR(__xludf.DUMMYFUNCTION("""COMPUTED_VALUE"""),11) -> 11 | B12: =IFERROR(__xludf.DUMMYFUNCTION("""COMPUTED_VALUE"""),"Indore City") -> Indore City | C12: =IFERROR(__xludf.DUMMYFUNCTION("""COMPUTED_VALUE"""),"JAIN ENTERPRISES") -> JAIN ENTERPRISES | D12: =IFERROR(__xludf.DUMMYFUNCTION("""COMPUTED_VALUE"""),1244430040) -> 1244430040 | E12: =IFERROR(__xludf.DUMMYFUNCTION("""COMPUTED_VALUE"""),46136) -> 46136 | G12: =IFERROR(__xludf.DUMMYFUNCTION("""COMPUTED_VALUE"""),"B2C") -> B2C | H12: =IFERROR(__xludf.DUMMYFUNCTION("""COMPUTED_VALUE"""),"Jalaj Rawat") -> Jalaj Rawat
A13: =IFERROR(__xludf.DUMMYFUNCTION("""COMPUTED_VALUE"""),12) -> 12 | B13: =IFERROR(__xludf.DUMMYFUNCTION("""COMPUTED_VALUE"""),"Indore City") -> Indore City | C13: =IFERROR(__xludf.DUMMYFUNCTION("""COMPUTED_VALUE"""),"LASNARO AGROVET PRIVATE LIMITED") -> LASNARO AGROVET PRIVATE LIMITED | D13: =IFERROR(__xludf.DUMMYFUNCTION("""COMPUTED_VALUE"""),1335697406) -> 1335697406 | E13: =IFERROR(__xludf.DUMMYFUNCTION("""COMPUTED_VALUE"""),46136) -> 46136 | G13: =IFERROR(__xludf.DUMMYFUNCTION("""COMPUTED_VALUE"""),"B2C") -> B2C | H13: =IFERROR(__xludf.DUMMYFUNCTION("""COMPUTED_VALUE"""),"Rahul Panchal") -> Rahul Panchal
A14: =IFERROR(__xludf.DUMMYFUNCTION("""COMPUTED_VALUE"""),13) -> 13 | B14: =IFERROR(__xludf.DUMMYFUNCTION("""COMPUTED_VALUE"""),"Indore City") -> Indore City | C14: =IFERROR(__xludf.DUMMYFUNCTION("""COMPUTED_VALUE"""),"Brain Box") -> Brain Box | D14: =IFERROR(__xludf.DUMMYFUNCTION("""COMPUTED_VALUE"""),1651181890) -> 1651181890 | E14: =IFERROR(__xludf.DUMMYFUNCTION("""COMPUTED_VALUE"""),46121) -> 46121 | G14: =IFERROR(__xludf.DUMMYFUNCTION("""COMPUTED_VALUE"""),"B2C") -> B2C | H14: =IFERROR(__xludf.DUMMYFUNCTION("""COMPUTED_VALUE"""),"Zuber Ahmed Khan") -> Zuber Ahmed Khan
A15: =IFERROR(__xludf.DUMMYFUNCTION("""COMPUTED_VALUE"""),14) -> 14 | B15: =IFERROR(__xludf.DUMMYFUNCTION("""COMPUTED_VALUE"""),"Indore City") -> Indore City | C15: =IFERROR(__xludf.DUMMYFUNCTION("""COMPUTED_VALUE"""),"SPNIWCD RC Indore") -> SPNIWCD RC Indore | D15: =IFERROR(__xludf.DUMMYFUNCTION("""COMPUTED_VALUE"""),1723023500) -> 1723023500 | E15: =IFERROR(__xludf.DUMMYFUNCTION("""COMPUTED_VALUE"""),46136) -> 46136 | G15: =IFERROR(__xludf.DUMMYFUNCTION("""COMPUTED_VALUE"""),"B2C") -> B2C | H15: =IFERROR(__xludf.DUMMYFUNCTION("""COMPUTED_VALUE"""),"Jalaj Rawat") -> Jalaj Rawat
A16: =IFERROR(__xludf.DUMMYFUNCTION("""COMPUTED_VALUE"""),15) -> 15 | B16: =IFERROR(__xludf.DUMMYFUNCTION("""COMPUTED_VALUE"""),"Indore City") -> Indore City | C16: =IFERROR(__xludf.DUMMYFUNCTION("""COMPUTED_VALUE"""),"govt. holkar science college") -> govt. holkar science college | D16: =IFERROR(__xludf.DUMMYFUNCTION("""COMPUTED_VALUE"""),1598560103) -> 1598560103 | E16: =IFERROR(__xludf.DUMMYFUNCTION("""COMPUTED_VALUE"""),46146) -> 46146 | G16: =IFERROR(__xludf.DUMMYFUNCTION("""COMPUTED_VALUE"""),"B2C") -> B2C | H16: =IFERROR(__xludf.DUMMYFUNCTION("""COMPUTED_VALUE"""),"Rahul Panchal") -> Rahul Panchal
A17: =IFERROR(__xludf.DUMMYFUNCTION("""COMPUTED_VALUE"""),16) -> 16 | B17: =IFERROR(__xludf.DUMMYFUNCTION("""COMPUTED_VALUE"""),"Indore City") -> Indore City | C17: =IFERROR(__xludf.DUMMYFUNCTION("""COMPUTED_VALUE"""),"NAVPRAN ENTERPRISES PVT LTD") -> NAVPRAN ENTERPRISES PVT LTD | D17: =IFERROR(__xludf.DUMMYFUNCTION("""COMPUTED_VALUE"""),1751940875) -> 1751940875 | E17: =IFERROR(__xludf.DUMMYFUNCTION("""COMPUTED_VALUE"""),46154) -> 46154 | G17: =IFERROR(__xludf.DUMMYFUNCTION("""COMPUTED_VALUE"""),"B2C") -> B2C | H17: =IFERROR(__xludf.DUMMYFUNCTION("""COMPUTED_VALUE"""),"Jalaj Rawat") -> Jalaj Rawat
A18: =IFERROR(__xludf.DUMMYFUNCTION("""COMPUTED_VALUE"""),17) -> 17 | B18: =IFERROR(__xludf.DUMMYFUNCTION("""COMPUTED_VALUE"""),"Indore City") -> Indore City | C18: =IFERROR(__xludf.DUMMYFUNCTION("""COMPUTED_VALUE"""),"AAHARSUDHI") -> AAHARSUDHI | D18: =IFERROR(__xludf.DUMMYFUNCTION("""COMPUTED_VALUE"""),1404760827) -> 1404760827 | E18: =IFERROR(__xludf.DUMMYFUNCTION("""COMPUTED_VALUE"""),46157) -> 46157 | G18: =IFERROR(__xludf.DUMMYFUNCTION("""COMPUTED_VALUE"""),"B2C") -> B2C | H18: =IFERROR(__xludf.DUMMYFUNCTION("""COMPUTED_VALUE"""),"Jalaj Rawat") -> Jalaj Rawat
A19: =IFERROR(__xludf.DUMMYFUNCTION("""COMPUTED_VALUE"""),18) -> 18 | B19: =IFERROR(__xludf.DUMMYFUNCTION("""COMPUTED_VALUE"""),"Indore City") -> Indore City | C19: =IFERROR(__xludf.DUMMYFUNCTION("""COMPUTED_VALUE"""),"DNHS HEAL THCARE DEVICES PRIVATE LIMITED") -> DNHS HEAL THCARE DEVICES PRIVATE LIMITED | D19: =IFERROR(__xludf.DUMMYFUNCTION("""COMPUTED_VALUE"""),1677646540) -> 1677646540 | E19: =IFERROR(__xludf.DUMMYFUNCTION("""COMPUTED_VALUE"""),46157) -> 46157 | G19: =IFERROR(__xludf.DUMMYFUNCTION("""COMPUTED_VALUE"""),"B2C") -> B2C | H19: =IFERROR(__xludf.DUMMYFUNCTION("""COMPUTED_VALUE"""),"Zuber Ahmed Khan") -> Zuber Ahmed Khan
A20: =IFERROR(__xludf.DUMMYFUNCTION("""COMPUTED_VALUE"""),19) -> 19 | B20: =IFERROR(__xludf.DUMMYFUNCTION("""COMPUTED_VALUE"""),"Indore City") -> Indore City | C20: =IFERROR(__xludf.DUMMYFUNCTION("""COMPUTED_VALUE"""),"RAHI COLLECTION") -> RAHI COLLECTION | D20: =IFERROR(__xludf.DUMMYFUNCTION("""COMPUTED_VALUE"""),1295229907) -> 1295229907 | E20: =IFERROR(__xludf.DUMMYFUNCTION("""COMPUTED_VALUE"""),46157) -> 46157 | G20: =IFERROR(__xludf.DUMMYFUNCTION("""COMPUTED_VALUE"""),"B2C") -> B2C | H20: =IFERROR(__xludf.DUMMYFUNCTION("""COMPUTED_VALUE"""),"Jalaj Rawat") -> Jalaj Rawat
A21: =IFERROR(__xludf.DUMMYFUNCTION("""COMPUTED_VALUE"""),20) -> 20 | B21: =IFERROR(__xludf.DUMMYFUNCTION("""COMPUTED_VALUE"""),"Indore City") -> Indore City | C21: =IFERROR(__xludf.DUMMYFUNCTION("""COMPUTED_VALUE"""),"Superb Apparels") -> Superb Apparels | D21: =IFERROR(__xludf.DUMMYFUNCTION("""COMPUTED_VALUE"""),1900618990) -> 1900618990 | E21: =IFERROR(__xludf.DUMMYFUNCTION("""COMPUTED_VALUE"""),46157) -> 46157 | G21: =IFERROR(__xludf.DUMMYFUNCTION("""COMPUTED_VALUE"""),"B2C") -> B2C | H21: =IFERROR(__xludf.DUMMYFUNCTION("""COMPUTED_VALUE"""),"Jalaj Rawat") -> Jalaj Rawat
A22: =IFERROR(__xludf.DUMMYFUNCTION("""COMPUTED_VALUE"""),21) -> 21 | B22: =IFERROR(__xludf.DUMMYFUNCTION("""COMPUTED_VALUE"""),"Indore City") -> Indore City | C22: =IFERROR(__xludf.DUMMYFUNCTION("""COMPUTED_VALUE"""),"SWASTIKA INVESTMART LIMITED") -> SWASTIKA INVESTMART LIMITED | D22: =IFERROR(__xludf.DUMMYFUNCTION("""COMPUTED_VALUE"""),1995115361) -> 1995115361 | E22: =IFERROR(__xludf.DUMMYFUNCTION("""COMPUTED_VALUE"""),46160) -> 46160 | G22: =IFERROR(__xludf.DUMMYFUNCTION("""COMPUTED_VALUE"""),"B2C") -> B2C | H22: =IFERROR(__xludf.DUMMYFUNCTION("""COMPUTED_VALUE"""),"Zuber Ahmed Khan") -> Zuber Ahmed Khan
A23: =IFERROR(__xludf.DUMMYFUNCTION("""COMPUTED_VALUE"""),22) -> 22 | B23: =IFERROR(__xludf.DUMMYFUNCTION("""COMPUTED_VALUE"""),"Indore City") -> Indore City | C23: =IFERROR(__xludf.DUMMYFUNCTION("""COMPUTED_VALUE"""),"CDTL Indore") -> CDTL Indore | D23: =IFERROR(__xludf.DUMMYFUNCTION("""COMPUTED_VALUE"""),1928644086) -> 1928644086 | E23: =IFERROR(__xludf.DUMMYFUNCTION("""COMPUTED_VALUE"""),46161) -> 46161 | G23: =IFERROR(__xludf.DUMMYFUNCTION("""COMPUTED_VALUE"""),"B2C") -> B2C | H23: =IFERROR(__xludf.DUMMYFUNCTION("""COMPUTED_VALUE"""),"Jalaj Rawat") -> Jalaj Rawat
A24: =IFERROR(__xludf.DUMMYFUNCTION("""COMPUTED_VALUE"""),23) -> 23 | B24: =IFERROR(__xludf.DUMMYFUNCTION("""COMPUTED_VALUE"""),"Indore City") -> Indore City | C24: =IFERROR(__xludf.DUMMYFUNCTION("""COMPUTED_VALUE"""),"ELEGANCE") -> ELEGANCE | D24: =IFERROR(__xludf.DUMMYFUNCTION("""COMPUTED_VALUE"""),1484254269) -> 1484254269 | E24: =IFERROR(__xludf.DUMMYFUNCTION("""COMPUTED_VALUE"""),46169) -> 46169 | G24: =IFERROR(__xludf.DUMMYFUNCTION("""COMPUTED_VALUE"""),"B2C") -> B2C | H24: =IFERROR(__xludf.DUMMYFUNCTION("""COMPUTED_VALUE"""),"Rahul Panchal") -> Rahul Panchal
A25: =IFERROR(__xludf.DUMMYFUNCTION("""COMPUTED_VALUE"""),24) -> 24 | B25: =IFERROR(__xludf.DUMMYFUNCTION("""COMPUTED_VALUE"""),"Indore City") -> Indore City | C25: =IFERROR(__xludf.DUMMYFUNCTION("""COMPUTED_VALUE"""),"Grandeur Ventures International") -> Grandeur Ventures International | D25: =IFERROR(__xludf.DUMMYFUNCTION("""COMPUTED_VALUE"""),1316759247) -> 1316759247 | E25: =IFERROR(__xludf.DUMMYFUNCTION("""COMPUTED_VALUE"""),46169) -> 46169 | G25: =IFERROR(__xludf.DUMMYFUNCTION("""COMPUTED_VALUE"""),"B2C") -> B2C | H25: =IFERROR(__xludf.DUMMYFUNCTION("""COMPUTED_VALUE"""),"Jalaj Rawat") -> Jalaj Rawat
A26: =IFERROR(__xludf.DUMMYFUNCTION("""COMPUTED_VALUE"""),25) -> 25 | B26: =IFERROR(__xludf.DUMMYFUNCTION("""COMPUTED_VALUE"""),"Indore City") -> Indore City | C26: =IFERROR(__xludf.DUMMYFUNCTION("""COMPUTED_VALUE"""),"INDIAN OVERSEAS BANK") -> INDIAN OVERSEAS BANK | D26: =IFERROR(__xludf.DUMMYFUNCTION("""COMPUTED_VALUE"""),1728296339) -> 1728296339 | E26: =IFERROR(__xludf.DUMMYFUNCTION("""COMPUTED_VALUE"""),46169) -> 46169 | G26: =IFERROR(__xludf.DUMMYFUNCTION("""COMPUTED_VALUE"""),"B2C") -> B2C | H26: =IFERROR(__xludf.DUMMYFUNCTION("""COMPUTED_VALUE"""),"Rahul Panchal") -> Rahul Panchal
A27: =IFERROR(__xludf.DUMMYFUNCTION("""COMPUTED_VALUE"""),26) -> 26 | B27: =IFERROR(__xludf.DUMMYFUNCTION("""COMPUTED_VALUE"""),"Indore City") -> Indore City | C27: =IFERROR(__xludf.DUMMYFUNCTION("""COMPUTED_VALUE"""),"LABU INTERNATIONAL") -> LABU INTERNATIONAL | D27: =IFERROR(__xludf.DUMMYFUNCTION("""COMPUTED_VALUE"""),1660828615) -> 1660828615 | E27: =IFERROR(__xludf.DUMMYFUNCTION("""COMPUTED_VALUE"""),46169) -> 46169 | G27: =IFERROR(__xludf.DUMMYFUNCTION("""COMPUTED_VALUE"""),"B2C") -> B2C | H27: =IFERROR(__xludf.DUMMYFUNCTION("""COMPUTED_VALUE"""),"Jalaj Rawat") -> Jalaj Rawat
A28: =IFERROR(__xludf.DUMMYFUNCTION("""COMPUTED_VALUE"""),27) -> 27 | B28: =IFERROR(__xludf.DUMMYFUNCTION("""COMPUTED_VALUE"""),"Indore City") -> Indore City | C28: =IFERROR(__xludf.DUMMYFUNCTION("""COMPUTED_VALUE"""),"SANJEEVANI AYURVEDIC") -> SANJEEVANI AYURVEDIC | D28: =IFERROR(__xludf.DUMMYFUNCTION("""COMPUTED_VALUE"""),1132126422) -> 1132126422 | E28: =IFERROR(__xludf.DUMMYFUNCTION("""COMPUTED_VALUE"""),46169) -> 46169 | G28: =IFERROR(__xludf.DUMMYFUNCTION("""COMPUTED_VALUE"""),"B2C") -> B2C | H28: =IFERROR(__xludf.DUMMYFUNCTION("""COMPUTED_VALUE"""),"Rahul Panchal") -> Rahul Panchal
A29: =IFERROR(__xludf.DUMMYFUNCTION("""COMPUTED_VALUE"""),28) -> 28 | B29: =IFERROR(__xludf.DUMMYFUNCTION("""COMPUTED_VALUE"""),"Indore City") -> Indore City | C29: =IFERROR(__xludf.DUMMYFUNCTION("""COMPUTED_VALUE"""),"STATE BANK OF INDIA HIGH COURT BRANCH") -> STATE BANK OF INDIA HIGH COURT BRANCH | D29: =IFERROR(__xludf.DUMMYFUNCTION("""COMPUTED_VALUE"""),1838482754) -> 1838482754 | E29: =IFERROR(__xludf.DUMMYFUNCTION("""COMPUTED_VALUE"""),46169) -> 46169 | G29: =IFERROR(__xludf.DUMMYFUNCTION("""COMPUTED_VALUE"""),"B2C") -> B2C | H29: =IFERROR(__xludf.DUMMYFUNCTION("""COMPUTED_VALUE"""),"Zuber Ahmed Khan") -> Zuber Ahmed Khan
A30: =IFERROR(__xludf.DUMMYFUNCTION("""COMPUTED_VALUE"""),29) -> 29 | B30: =IFERROR(__xludf.DUMMYFUNCTION("""COMPUTED_VALUE"""),"Indore City") -> Indore City | C30: =IFERROR(__xludf.DUMMYFUNCTION("""COMPUTED_VALUE"""),"Union Bank Of India Regal Square") -> Union Bank Of India Regal Square | D30: =IFERROR(__xludf.DUMMYFUNCTION("""COMPUTED_VALUE"""),1329301695) -> 1329301695 | E30: =IFERROR(__xludf.DUMMYFUNCTION("""COMPUTED_VALUE"""),46169) -> 46169 | G30: =IFERROR(__xludf.DUMMYFUNCTION("""COMPUTED_VALUE"""),"B2C") -> B2C | H30: =IFERROR(__xludf.DUMMYFUNCTION("""COMPUTED_VALUE"""),"Jalaj Rawat") -> Jalaj Rawat
A31: =IFERROR(__xludf.DUMMYFUNCTION("""COMPUTED_VALUE"""),30) -> 30 | B31: =IFERROR(__xludf.DUMMYFUNCTION("""COMPUTED_VALUE"""),"Indore City") -> Indore City | C31: =IFERROR(__xludf.DUMMYFUNCTION("""COMPUTED_VALUE"""),"Indusind General Insurance Company Ltd") -> Indusind General Insurance Company Ltd | D31: =IFERROR(__xludf.DUMMYFUNCTION("""COMPUTED_VALUE"""),3000009588) -> 3000009588 | E31: =IFERROR(__xludf.DUMMYFUNCTION("""COMPUTED_VALUE"""),46174) -> 46174 | G31: =IFERROR(__xludf.DUMMYFUNCTION("""COMPUTED_VALUE"""),"B2C") -> B2C | H31: =IFERROR(__xludf.DUMMYFUNCTION("""COMPUTED_VALUE"""),"Jalaj Rawat") -> Jalaj Rawat
A32: =IFERROR(__xludf.DUMMYFUNCTION("""COMPUTED_VALUE"""),31) -> 31 | B32: =IFERROR(__xludf.DUMMYFUNCTION("""COMPUTED_VALUE"""),"Indore City") -> Indore City | C32: =IFERROR(__xludf.DUMMYFUNCTION("""COMPUTED_VALUE"""),"SIPL DATA SERVICES") -> SIPL DATA SERVICES | D32: =IFERROR(__xludf.DUMMYFUNCTION("""COMPUTED_VALUE"""),1804236062) -> 1804236062 | E32: =IFERROR(__xludf.DUMMYFUNCTION("""COMPUTED_VALUE"""),46174) -> 46174 | G32: =IFERROR(__xludf.DUMMYFUNCTION("""COMPUTED_VALUE"""),"B2C") -> B2C | H32: =IFERROR(__xludf.DUMMYFUNCTION("""COMPUTED_VALUE"""),"Jalaj Rawat") -> Jalaj Rawat
A33: =IFERROR(__xludf.DUMMYFUNCTION("""COMPUTED_VALUE"""),32) -> 32 | B33: =IFERROR(__xludf.DUMMYFUNCTION("""COMPUTED_VALUE"""),"Indore City") -> Indore City | C33: =IFERROR(__xludf.DUMMYFUNCTION("""COMPUTED_VALUE"""),"National insurance co. Ltd. IRO") -> National insurance co. Ltd. IRO | D33: =IFERROR(__xludf.DUMMYFUNCTION("""COMPUTED_VALUE"""),1161465239) -> 1161465239 | E33: =IFERROR(__xludf.DUMMYFUNCTION("""COMPUTED_VALUE"""),46176) -> 46176 | G33: =IFERROR(__xludf.DUMMYFUNCTION("""COMPUTED_VALUE"""),"B2C") -> B2C | H33: =IFERROR(__xludf.DUMMYFUNCTION("""COMPUTED_VALUE"""),"Jalaj Rawat") -> Jalaj Rawat
A34: =IFERROR(__xludf.DUMMYFUNCTION("""COMPUTED_VALUE"""),33) -> 33 | B34: =IFERROR(__xludf.DUMMYFUNCTION("""COMPUTED_VALUE"""),"Indore City") -> Indore City | C34: =IFERROR(__xludf.DUMMYFUNCTION("""COMPUTED_VALUE"""),"FIT FOR MAN") -> FIT FOR MAN | D34: =IFERROR(__xludf.DUMMYFUNCTION("""COMPUTED_VALUE"""),1533129385) -> 1533129385 | E34: =IFERROR(__xludf.DUMMYFUNCTION("""COMPUTED_VALUE"""),46182) -> 46182 | G34: =IFERROR(__xludf.DUMMYFUNCTION("""COMPUTED_VALUE"""),"B2C") -> B2C | H34: =IFERROR(__xludf.DUMMYFUNCTION("""COMPUTED_VALUE"""),"Zuber Ahmed Khan") -> Zuber Ahmed Khan
A35: =IFERROR(__xludf.DUMMYFUNCTION("""COMPUTED_VALUE"""),34) -> 34 | B35: =IFERROR(__xludf.DUMMYFUNCTION("""COMPUTED_VALUE"""),"Indore City") -> Indore City | C35: =IFERROR(__xludf.DUMMYFUNCTION("""COMPUTED_VALUE"""),"LAKSHYA OVERSEAS EDUCATION") -> LAKSHYA OVERSEAS EDUCATION | D35: =IFERROR(__xludf.DUMMYFUNCTION("""COMPUTED_VALUE"""),1129271649) -> 1129271649 | E35: =IFERROR(__xludf.DUMMYFUNCTION("""COMPUTED_VALUE"""),46182) -> 46182 | G35: =IFERROR(__xludf.DUMMYFUNCTION("""COMPUTED_VALUE"""),"B2C") -> B2C | H35: =IFERROR(__xludf.DUMMYFUNCTION("""COMPUTED_VALUE"""),"Rahul Panchal") -> Rahul Panchal
A36: =IFERROR(__xludf.DUMMYFUNCTION("""COMPUTED_VALUE"""),35) -> 35 | B36: =IFERROR(__xludf.DUMMYFUNCTION("""COMPUTED_VALUE"""),"Indore City") -> Indore City | C36: =IFERROR(__xludf.DUMMYFUNCTION("""COMPUTED_VALUE"""),"Patanjali Foods Limited") -> Patanjali Foods Limited | D36: =IFERROR(__xludf.DUMMYFUNCTION("""COMPUTED_VALUE"""),1422857286) -> 1422857286 | E36: =IFERROR(__xludf.DUMMYFUNCTION("""COMPUTED_VALUE"""),46182) -> 46182 | G36: =IFERROR(__xludf.DUMMYFUNCTION("""COMPUTED_VALUE"""),"B2C") -> B2C | H36: =IFERROR(__xludf.DUMMYFUNCTION("""COMPUTED_VALUE"""),"Jalaj Rawat") -> Jalaj Rawat
A37: =IFERROR(__xludf.DUMMYFUNCTION("""COMPUTED_VALUE"""),36) -> 36 | B37: =IFERROR(__xludf.DUMMYFUNCTION("""COMPUTED_VALUE"""),"Indore City") -> Indore City | C37: =IFERROR(__xludf.DUMMYFUNCTION("""COMPUTED_VALUE"""),"Union Bank of India ARB Branch") -> Union Bank of India ARB Branch | D37: =IFERROR(__xludf.DUMMYFUNCTION("""COMPUTED_VALUE"""),1943080486) -> 1943080486 | E37: =IFERROR(__xludf.DUMMYFUNCTION("""COMPUTED_VALUE"""),46182) -> 46182 | G37: =IFERROR(__xludf.DUMMYFUNCTION("""COMPUTED_VALUE"""),"B2C") -> B2C | H37: =IFERROR(__xludf.DUMMYFUNCTION("""COMPUTED_VALUE"""),"Zuber Ahmed Khan") -> Zuber Ahmed Khan
A38: =IFERROR(__xludf.DUMMYFUNCTION("""COMPUTED_VALUE"""),37) -> 37 | B38: =IFERROR(__xludf.DUMMYFUNCTION("""COMPUTED_VALUE"""),"Indore City") -> Indore City | C38: =IFERROR(__xludf.DUMMYFUNCTION("""COMPUTED_VALUE"""),"VATYA THE LABEL") -> VATYA THE LABEL | D38: =IFERROR(__xludf.DUMMYFUNCTION("""COMPUTED_VALUE"""),1188407437) -> 1188407437 | E38: =IFERROR(__xludf.DUMMYFUNCTION("""COMPUTED_VALUE"""),46182) -> 46182 | G38: =IFERROR(__xludf.DUMMYFUNCTION("""COMPUTED_VALUE"""),"B2C") -> B2C | H38: =IFERROR(__xludf.DUMMYFUNCTION("""COMPUTED_VALUE"""),"Rahul Panchal") -> Rahul Panchal
A39: =IFERROR(__xludf.DUMMYFUNCTION("""COMPUTED_VALUE"""),38) -> 38 | B39: =IFERROR(__xludf.DUMMYFUNCTION("""COMPUTED_VALUE"""),"Indore City") -> Indore City | C39: =IFERROR(__xludf.DUMMYFUNCTION("""COMPUTED_VALUE"""),"MUKUL LEARNING SYSTEMS LLP") -> MUKUL LEARNING SYSTEMS LLP | D39: =IFERROR(__xludf.DUMMYFUNCTION("""COMPUTED_VALUE"""),1808596663) -> 1808596663 | E39: =IFERROR(__xludf.DUMMYFUNCTION("""COMPUTED_VALUE"""),46195) -> 46195 | G39: =IFERROR(__xludf.DUMMYFUNCTION("""COMPUTED_VALUE"""),"B2C") -> B2C | H39: =IFERROR(__xludf.DUMMYFUNCTION("""COMPUTED_VALUE"""),"Zuber Ahmed Khan") -> Zuber Ahmed Khan
A40: =IFERROR(__xludf.DUMMYFUNCTION("""COMPUTED_VALUE"""),39) -> 39 | B40: =IFERROR(__xludf.DUMMYFUNCTION("""COMPUTED_VALUE"""),"Indore City") -> Indore City | C40: =IFERROR(__xludf.DUMMYFUNCTION("""COMPUTED_VALUE"""),"The Easy Shopping") -> The Easy Shopping | D40: =IFERROR(__xludf.DUMMYFUNCTION("""COMPUTED_VALUE"""),1583054640) -> 1583054640 | E40: =IFERROR(__xludf.DUMMYFUNCTION("""COMPUTED_VALUE"""),46195) -> 46195 | G40: =IFERROR(__xludf.DUMMYFUNCTION("""COMPUTED_VALUE"""),"B2C") -> B2C | H40: =IFERROR(__xludf.DUMMYFUNCTION("""COMPUTED_VALUE"""),"Rahul Panchal") -> Rahul Panchal
A41: =IFERROR(__xludf.DUMMYFUNCTION("""COMPUTED_VALUE"""),40) -> 40 | B41: =IFERROR(__xludf.DUMMYFUNCTION("""COMPUTED_VALUE"""),"Indore City") -> Indore City | C41: =IFERROR(__xludf.DUMMYFUNCTION("""COMPUTED_VALUE"""),"champion square") -> champion square | D41: =IFERROR(__xludf.DUMMYFUNCTION("""COMPUTED_VALUE"""),1234253895) -> 1234253895 | E41: =IFERROR(__xludf.DUMMYFUNCTION("""COMPUTED_VALUE"""),46197) -> 46197 | G41: =IFERROR(__xludf.DUMMYFUNCTION("""COMPUTED_VALUE"""),"B2C") -> B2C | H41: =IFERROR(__xludf.DUMMYFUNCTION("""COMPUTED_VALUE"""),"Rahul Panchal") -> Rahul Panchal
A42: =IFERROR(__xludf.DUMMYFUNCTION("""COMPUTED_VALUE"""),41) -> 41 | B42: =IFERROR(__xludf.DUMMYFUNCTION("""COMPUTED_VALUE"""),"Indore City") -> Indore City | C42: =IFERROR(__xludf.DUMMYFUNCTION("""COMPUTED_VALUE"""),"JK AGRO INPUTS LLP") -> JK AGRO INPUTS LLP | D42: =IFERROR(__xludf.DUMMYFUNCTION("""COMPUTED_VALUE"""),1296712458) -> 1296712458 | E42: =IFERROR(__xludf.DUMMYFUNCTION("""COMPUTED_VALUE"""),46197) -> 46197 | G42: =IFERROR(__xludf.DUMMYFUNCTION("""COMPUTED_VALUE"""),"B2C") -> B2C | H42: =IFERROR(__xludf.DUMMYFUNCTION("""COMPUTED_VALUE"""),"Rahul Panchal") -> Rahul Panchal
A43: =IFERROR(__xludf.DUMMYFUNCTION("""COMPUTED_VALUE"""),42) -> 42 | B43: =IFERROR(__xludf.DUMMYFUNCTION("""COMPUTED_VALUE"""),"Indore City") -> Indore City | C43: =IFERROR(__xludf.DUMMYFUNCTION("""COMPUTED_VALUE"""),"MONTI ENTERPRISES") -> MONTI ENTERPRISES | D43: =IFERROR(__xludf.DUMMYFUNCTION("""COMPUTED_VALUE"""),1909759008) -> 1909759008 | E43: =IFERROR(__xludf.DUMMYFUNCTION("""COMPUTED_VALUE"""),46197) -> 46197 | G43: =IFERROR(__xludf.DUMMYFUNCTION("""COMPUTED_VALUE"""),"B2C") -> B2C | H43: =IFERROR(__xludf.DUMMYFUNCTION("""COMPUTED_VALUE"""),"Jalaj Rawat") -> Jalaj Rawat
A44: =IFERROR(__xludf.DUMMYFUNCTION("""COMPUTED_VALUE"""),43) -> 43 | B44: =IFERROR(__xludf.DUMMYFUNCTION("""COMPUTED_VALUE"""),"Indore City") -> Indore City | C44: =IFERROR(__xludf.DUMMYFUNCTION("""COMPUTED_VALUE"""),"NIROGYA JEEVAN") -> NIROGYA JEEVAN | D44: =IFERROR(__xludf.DUMMYFUNCTION("""COMPUTED_VALUE"""),1160587323) -> 1160587323 | E44: =IFERROR(__xludf.DUMMYFUNCTION("""COMPUTED_VALUE"""),46197) -> 46197 | G44: =IFERROR(__xludf.DUMMYFUNCTION("""COMPUTED_VALUE"""),"B2C") -> B2C | H44: =IFERROR(__xludf.DUMMYFUNCTION("""COMPUTED_VALUE"""),"Zuber Ahmed Khan") -> Zuber Ahmed Khan
A45: =IFERROR(__xludf.DUMMYFUNCTION("""COMPUTED_VALUE"""),44) -> 44 | B45: =IFERROR(__xludf.DUMMYFUNCTION("""COMPUTED_VALUE"""),"Indore City") -> Indore City | C45: =IFERROR(__xludf.DUMMYFUNCTION("""COMPUTED_VALUE"""),"PADMAKAR HANDCRAFTED SOAP") -> PADMAKAR HANDCRAFTED SOAP | D45: =IFERROR(__xludf.DUMMYFUNCTION("""COMPUTED_VALUE"""),1743018894) -> 1743018894 | E45: =IFERROR(__xludf.DUMMYFUNCTION("""COMPUTED_VALUE"""),46197) -> 46197 | G45: =IFERROR(__xludf.DUMMYFUNCTION("""COMPUTED_VALUE"""),"B2C") -> B2C | H45: =IFERROR(__xludf.DUMMYFUNCTION("""COMPUTED_VALUE"""),"Zuber Ahmed Khan") -> Zuber Ahmed Khan
A46: =IFERROR(__xludf.DUMMYFUNCTION("""COMPUTED_VALUE"""),45) -> 45 | B46: =IFERROR(__xludf.DUMMYFUNCTION("""COMPUTED_VALUE"""),"Indore City") -> Indore City | C46: =IFERROR(__xludf.DUMMYFUNCTION("""COMPUTED_VALUE"""),"TRP COTTON LINAN") -> TRP COTTON LINAN | D46: =IFERROR(__xludf.DUMMYFUNCTION("""COMPUTED_VALUE"""),1845228720) -> 1845228720 | E46: =IFERROR(__xludf.DUMMYFUNCTION("""COMPUTED_VALUE"""),46197) -> 46197 | G46: =IFERROR(__xludf.DUMMYFUNCTION("""COMPUTED_VALUE"""),"B2C") -> B2C | H46: =IFERROR(__xludf.DUMMYFUNCTION("""COMPUTED_VALUE"""),"Jalaj Rawat") -> Jalaj Rawat
A47: =IFERROR(__xludf.DUMMYFUNCTION("""COMPUTED_VALUE"""),46) -> 46 | B47: =IFERROR(__xludf.DUMMYFUNCTION("""COMPUTED_VALUE"""),"Indore City") -> Indore City | C47: =IFERROR(__xludf.DUMMYFUNCTION("""COMPUTED_VALUE"""),"SHRI BALAJI ENTERPRISES") -> SHRI BALAJI ENTERPRISES | D47: =IFERROR(__xludf.DUMMYFUNCTION("""COMPUTED_VALUE"""),1133832663) -> 1133832663 | E47: =IFERROR(__xludf.DUMMYFUNCTION("""COMPUTED_VALUE"""),46203) -> 46203 | G47: =IFERROR(__xludf.DUMMYFUNCTION("""COMPUTED_VALUE"""),"B2C") -> B2C | H47: =IFERROR(__xludf.DUMMYFUNCTION("""COMPUTED_VALUE"""),"Rahul Panchal") -> Rahul Panchal
A48: =IFERROR(__xludf.DUMMYFUNCTION("""COMPUTED_VALUE"""),47) -> 47 | B48: =IFERROR(__xludf.DUMMYFUNCTION("""COMPUTED_VALUE"""),"Indore City") -> Indore City | C48: =IFERROR(__xludf.DUMMYFUNCTION("""COMPUTED_VALUE"""),"UNIK NATURALS") -> UNIK NATURALS | D48: =IFERROR(__xludf.DUMMYFUNCTION("""COMPUTED_VALUE"""),1913063058) -> 1913063058 | E48: =IFERROR(__xludf.DUMMYFUNCTION("""COMPUTED_VALUE"""),46203) -> 46203 | G48: =IFERROR(__xludf.DUMMYFUNCTION("""COMPUTED_VALUE"""),"B2C") -> B2C | H48: =IFERROR(__xludf.DUMMYFUNCTION("""COMPUTED_VALUE"""),"Jalaj Rawat") -> Jalaj Rawat
A49: =IFERROR(__xludf.DUMMYFUNCTION("""COMPUTED_VALUE"""),48) -> 48 | B49: =IFERROR(__xludf.DUMMYFUNCTION("""COMPUTED_VALUE"""),"Indore City") -> Indore City | C49: =IFERROR(__xludf.DUMMYFUNCTION("""COMPUTED_VALUE"""),"Deliverdas Jyayase Pvt Ltd") -> Deliverdas Jyayase Pvt Ltd | D49: =IFERROR(__xludf.DUMMYFUNCTION("""COMPUTED_VALUE"""),1425585353) -> 1425585353 | E49: =IFERROR(__xludf.DUMMYFUNCTION("""COMPUTED_VALUE"""),46204) -> 46204 | G49: =IFERROR(__xludf.DUMMYFUNCTION("""COMPUTED_VALUE"""),"B2C") -> B2C | H49: =IFERROR(__xludf.DUMMYFUNCTION("""COMPUTED_VALUE"""),"Jalaj Rawat") -> Jalaj Rawat
A50: =IFERROR(__xludf.DUMMYFUNCTION("""COMPUTED_VALUE"""),49) -> 49 | B50: =IFERROR(__xludf.DUMMYFUNCTION("""COMPUTED_VALUE"""),"Indore City") -> Indore City | C50: =IFERROR(__xludf.DUMMYFUNCTION("""COMPUTED_VALUE"""),"Lebroid healthcare PVT LTD") -> Lebroid healthcare PVT LTD | D50: =IFERROR(__xludf.DUMMYFUNCTION("""COMPUTED_VALUE"""),1950123528) -> 1950123528 | E50: =IFERROR(__xludf.DUMMYFUNCTION("""COMPUTED_VALUE"""),46205) -> 46205 | G50: =IFERROR(__xludf.DUMMYFUNCTION("""COMPUTED_VALUE"""),"B2C") -> B2C | H50: =IFERROR(__xludf.DUMMYFUNCTION("""COMPUTED_VALUE"""),"Jalaj Rawat") -> Jalaj Rawat
A51: =IFERROR(__xludf.DUMMYFUNCTION("""COMPUTED_VALUE"""),50) -> 50 | B51: =IFERROR(__xludf.DUMMYFUNCTION("""COMPUTED_VALUE"""),"Indore City") -> Indore City | C51: =IFERROR(__xludf.DUMMYFUNCTION("""COMPUTED_VALUE"""),"ALPHA ACADEMY") -> ALPHA ACADEMY | D51: =IFERROR(__xludf.DUMMYFUNCTION("""COMPUTED_VALUE"""),1170830433) -> 1170830433 | E51: =IFERROR(__xludf.DUMMYFUNCTION("""COMPUTED_VALUE"""),46209) -> 46209 | G51: =IFERROR(__xludf.DUMMYFUNCTION("""COMPUTED_VALUE"""),"B2C") -> B2C | H51: =IFERROR(__xludf.DUMMYFUNCTION("""COMPUTED_VALUE"""),"Rahul Panchal") -> Rahul Panchal
A52: =IFERROR(__xludf.DUMMYFUNCTION("""COMPUTED_VALUE"""),51) -> 51 | B52: =IFERROR(__xludf.DUMMYFUNCTION("""COMPUTED_VALUE"""),"Indore City") -> Indore City | C52: =IFERROR(__xludf.DUMMYFUNCTION("""COMPUTED_VALUE"""),"AVIKA ENTERPRISES") -> AVIKA ENTERPRISES | D52: =IFERROR(__xludf.DUMMYFUNCTION("""COMPUTED_VALUE"""),1193283934) -> 1193283934 | E52: =IFERROR(__xludf.DUMMYFUNCTION("""COMPUTED_VALUE"""),46209) -> 46209 | G52: =IFERROR(__xludf.DUMMYFUNCTION("""COMPUTED_VALUE"""),"B2C") -> B2C | H52: =IFERROR(__xludf.DUMMYFUNCTION("""COMPUTED_VALUE"""),"Rahul Panchal") -> Rahul Panchal
A53: =IFERROR(__xludf.DUMMYFUNCTION("""COMPUTED_VALUE"""),52) -> 52 | B53: =IFERROR(__xludf.DUMMYFUNCTION("""COMPUTED_VALUE"""),"Indore City") -> Indore City | C53: =IFERROR(__xludf.DUMMYFUNCTION("""COMPUTED_VALUE"""),"KISAN4U MARKETING PVT LTD") -> KISAN4U MARKETING PVT LTD | D53: =IFERROR(__xludf.DUMMYFUNCTION("""COMPUTED_VALUE"""),1929493007) -> 1929493007 | E53: =IFERROR(__xludf.DUMMYFUNCTION("""COMPUTED_VALUE"""),46216) -> 46216 | G53: =IFERROR(__xludf.DUMMYFUNCTION("""COMPUTED_VALUE"""),"B2C") -> B2C | H53: =IFERROR(__xludf.DUMMYFUNCTION("""COMPUTED_VALUE"""),"Jalaj Rawat") -> Jalaj Rawat
A54: =IFERROR(__xludf.DUMMYFUNCTION("""COMPUTED_VALUE"""),53) -> 53 | B54: =IFERROR(__xludf.DUMMYFUNCTION("""COMPUTED_VALUE"""),"Indore City") -> Indore City | C54: =IFERROR(__xludf.DUMMYFUNCTION("""COMPUTED_VALUE"""),"MAARENUKA FOODS PVT LTD") -> MAARENUKA FOODS PVT LTD | D54: =IFERROR(__xludf.DUMMYFUNCTION("""COMPUTED_VALUE"""),1000139830) -> 1000139830 | E54: =IFERROR(__xludf.DUMMYFUNCTION("""COMPUTED_VALUE"""),46216) -> 46216 | G54: =IFERROR(__xludf.DUMMYFUNCTION("""COMPUTED_VALUE"""),"B2C") -> B2C | H54: =IFERROR(__xludf.DUMMYFUNCTION("""COMPUTED_VALUE"""),"Rahul Panchal") -> Rahul Panchal
A55: =IFERROR(__xludf.DUMMYFUNCTION("""COMPUTED_VALUE"""),54) -> 54 | B55: =IFERROR(__xludf.DUMMYFUNCTION("""COMPUTED_VALUE"""),"Indore City") -> Indore City | C55: =IFERROR(__xludf.DUMMYFUNCTION("""COMPUTED_VALUE"""),"SE CPWD INDORE") -> SE CPWD INDORE | D55: =IFERROR(__xludf.DUMMYFUNCTION("""COMPUTED_VALUE"""),1363703562) -> 1363703562 | E55: =IFERROR(__xludf.DUMMYFUNCTION("""COMPUTED_VALUE"""),46216) -> 46216 | G55: =IFERROR(__xludf.DUMMYFUNCTION("""COMPUTED_VALUE"""),"B2C") -> B2C | H55: =IFERROR(__xludf.DUMMYFUNCTION("""COMPUTED_VALUE"""),"Zuber Ahmed Khan") -> Zuber Ahmed Khan
A56: =IFERROR(__xludf.DUMMYFUNCTION("""COMPUTED_VALUE"""),55) -> 55 | B56: =IFERROR(__xludf.DUMMYFUNCTION("""COMPUTED_VALUE"""),"Indore City") -> Indore City | C56: =IFERROR(__xludf.DUMMYFUNCTION("""COMPUTED_VALUE"""),"ALMIGHTY ORGANICS PRIVATE LIMITED") -> ALMIGHTY ORGANICS PRIVATE LIMITED | D56: =IFERROR(__xludf.DUMMYFUNCTION("""COMPUTED_VALUE"""),1735125629) -> 1735125629 | E56: =IFERROR(__xludf.DUMMYFUNCTION("""COMPUTED_VALUE"""),46218) -> 46218 | G56: =IFERROR(__xludf.DUMMYFUNCTION("""COMPUTED_VALUE"""),"B2C") -> B2C | H56: =IFERROR(__xludf.DUMMYFUNCTION("""COMPUTED_VALUE"""),"Zuber Ahmed Khan") -> Zuber Ahmed Khan
A57: =IFERROR(__xludf.DUMMYFUNCTION("""COMPUTED_VALUE"""),56) -> 56 | B57: =IFERROR(__xludf.DUMMYFUNCTION("""COMPUTED_VALUE"""),"Indore City") -> Indore City | C57: =IFERROR(__xludf.DUMMYFUNCTION("""COMPUTED_VALUE"""),"DITVI EXPORTS PVT LTD") -> DITVI EXPORTS PVT LTD | D57: =IFERROR(__xludf.DUMMYFUNCTION("""COMPUTED_VALUE"""),1417168016) -> 1417168016 | E57: =IFERROR(__xludf.DUMMYFUNCTION("""COMPUTED_VALUE"""),46218) -> 46218 | G57: =IFERROR(__xludf.DUMMYFUNCTION("""COMPUTED_VALUE"""),"B2C") -> B2C | H57: =IFERROR(__xludf.DUMMYFUNCTION("""COMPUTED_VALUE"""),"Jalaj Rawat") -> Jalaj Rawat
A58: =IFERROR(__xludf.DUMMYFUNCTION("""COMPUTED_VALUE"""),57) -> 57 | B58: =IFERROR(__xludf.DUMMYFUNCTION("""COMPUTED_VALUE"""),"Indore City") -> Indore City | C58: =IFERROR(__xludf.DUMMYFUNCTION("""COMPUTED_VALUE"""),"Madhur Courier Services") -> Madhur Courier Services | D58: =IFERROR(__xludf.DUMMYFUNCTION("""COMPUTED_VALUE"""),1952816963) -> 1952816963 | E58: =IFERROR(__xludf.DUMMYFUNCTION("""COMPUTED_VALUE"""),46218) -> 46218 | G58: =IFERROR(__xludf.DUMMYFUNCTION("""COMPUTED_VALUE"""),"B2B") -> B2B | H58: =IFERROR(__xludf.DUMMYFUNCTION("""COMPUTED_VALUE"""),"Jalaj Rawat") -> Jalaj Rawat
A59: =IFERROR(__xludf.DUMMYFUNCTION("""COMPUTED_VALUE"""),58) -> 58 | B59: =IFERROR(__xludf.DUMMYFUNCTION("""COMPUTED_VALUE"""),"Indore City") -> Indore City | C59: =IFERROR(__xludf.DUMMYFUNCTION("""COMPUTED_VALUE"""),"RIAA MEHENDI") -> RIAA MEHENDI | D59: =IFERROR(__xludf.DUMMYFUNCTION("""COMPUTED_VALUE"""),1100842696) -> 1100842696 | E59: =IFERROR(__xludf.DUMMYFUNCTION("""COMPUTED_VALUE"""),46226) -> 46226 | G59: =IFERROR(__xludf.DUMMYFUNCTION("""COMPUTED_VALUE"""),"B2C") -> B2C | H59: =IFERROR(__xludf.DUMMYFUNCTION("""COMPUTED_VALUE"""),"Rahul Panchal") -> Rahul Panchal
A60: =IFERROR(__xludf.DUMMYFUNCTION("""COMPUTED_VALUE"""),59) -> 59 | B60: =IFERROR(__xludf.DUMMYFUNCTION("""COMPUTED_VALUE"""),"Indore City") -> Indore City | C60: =IFERROR(__xludf.DUMMYFUNCTION("""COMPUTED_VALUE"""),"SAWARNA BY HEER") -> SAWARNA BY HEER | D60: =IFERROR(__xludf.DUMMYFUNCTION("""COMPUTED_VALUE"""),1503880606) -> 1503880606 | E60: =IFERROR(__xludf.DUMMYFUNCTION("""COMPUTED_VALUE"""),46226) -> 46226 | G60: =IFERROR(__xludf.DUMMYFUNCTION("""COMPUTED_VALUE"""),"B2C") -> B2C | H60: =IFERROR(__xludf.DUMMYFUNCTION("""COMPUTED_VALUE"""),"Rahul Panchal") -> Rahul Panchal
A61: =IFERROR(__xludf.DUMMYFUNCTION("""COMPUTED_VALUE"""),60) -> 60 | B61: =IFERROR(__xludf.DUMMYFUNCTION("""COMPUTED_VALUE"""),"Indore City") -> Indore City | C61: =IFERROR(__xludf.DUMMYFUNCTION("""COMPUTED_VALUE"""),"THE VAIDIK") -> THE VAIDIK | D61: =IFERROR(__xludf.DUMMYFUNCTION("""COMPUTED_VALUE"""),1127334021) -> 1127334021 | E61: =IFERROR(__xludf.DUMMYFUNCTION("""COMPUTED_VALUE"""),46226) -> 46226 | G61: =IFERROR(__xludf.DUMMYFUNCTION("""COMPUTED_VALUE"""),"B2C") -> B2C | H61: =IFERROR(__xludf.DUMMYFUNCTION("""COMPUTED_VALUE"""),"Jalaj Rawat") -> Jalaj Rawat
A62: =IFERROR(__xludf.DUMMYFUNCTION("""COMPUTED_VALUE"""),61) -> 61 | B62: =IFERROR(__xludf.DUMMYFUNCTION("""COMPUTED_VALUE"""),"Indore City") -> Indore City | C62: =IFERROR(__xludf.DUMMYFUNCTION("""COMPUTED_VALUE"""),"DYNAMECH ENGINEERS") -> DYNAMECH ENGINEERS | D62: =IFERROR(__xludf.DUMMYFUNCTION("""COMPUTED_VALUE"""),1713538732) -> 1713538732 | E62: =IFERROR(__xludf.DUMMYFUNCTION("""COMPUTED_VALUE"""),46232) -> 46232 | G62: =IFERROR(__xludf.DUMMYFUNCTION("""COMPUTED_VALUE"""),"B2C") -> B2C | H62: =IFERROR(__xludf.DUMMYFUNCTION("""COMPUTED_VALUE"""),"Jalaj Rawat") -> Jalaj Rawat
A63: =IFERROR(__xludf.DUMMYFUNCTION("""COMPUTED_VALUE"""),62) -> 62 | B63: =IFERROR(__xludf.DUMMYFUNCTION("""COMPUTED_VALUE"""),"Indore City") -> Indore City | C63: =IFERROR(__xludf.DUMMYFUNCTION("""COMPUTED_VALUE"""),"HANSHIKA CORPORATION") -> HANSHIKA CORPORATION | D63: =IFERROR(__xludf.DUMMYFUNCTION("""COMPUTED_VALUE"""),1581886034) -> 1581886034 | E63: =IFERROR(__xludf.DUMMYFUNCTION("""COMPUTED_VALUE"""),46232) -> 46232 | G63: =IFERROR(__xludf.DUMMYFUNCTION("""COMPUTED_VALUE"""),"B2C") -> B2C | H63: =IFERROR(__xludf.DUMMYFUNCTION("""COMPUTED_VALUE"""),"Jalaj Rawat") -> Jalaj Rawat
A64: =IFERROR(__xludf.DUMMYFUNCTION("""COMPUTED_VALUE"""),63) -> 63 | B64: =IFERROR(__xludf.DUMMYFUNCTION("""COMPUTED_VALUE"""),"Indore City") -> Indore City | C64: =IFERROR(__xludf.DUMMYFUNCTION("""COMPUTED_VALUE"""),"HPCL LPG RO INDORE") -> HPCL LPG RO INDORE | D64: =IFERROR(__xludf.DUMMYFUNCTION("""COMPUTED_VALUE"""),1261051215) -> 1261051215 | E64: =IFERROR(__xludf.DUMMYFUNCTION("""COMPUTED_VALUE"""),46232) -> 46232 | G64: =IFERROR(__xludf.DUMMYFUNCTION("""COMPUTED_VALUE"""),"B2C") -> B2C | H64: =IFERROR(__xludf.DUMMYFUNCTION("""COMPUTED_VALUE"""),"Jalaj Rawat") -> Jalaj Rawat
A65: =IFERROR(__xludf.DUMMYFUNCTION("""COMPUTED_VALUE"""),64) -> 64 | B65: =IFERROR(__xludf.DUMMYFUNCTION("""COMPUTED_VALUE"""),"Indore City") -> Indore City | C65: =IFERROR(__xludf.DUMMYFUNCTION("""COMPUTED_VALUE"""),"NIACL INDORE LBO") -> NIACL INDORE LBO | D65: =IFERROR(__xludf.DUMMYFUNCTION("""COMPUTED_VALUE"""),1881278509) -> 1881278509 | E65: =IFERROR(__xludf.DUMMYFUNCTION("""COMPUTED_VALUE"""),46232) -> 46232 | G65: =IFERROR(__xludf.DUMMYFUNCTION("""COMPUTED_VALUE"""),"B2C") -> B2C | H65: =IFERROR(__xludf.DUMMYFUNCTION("""COMPUTED_VALUE"""),"Jalaj Rawat") -> Jalaj Rawat
A66: =IFERROR(__xludf.DUMMYFUNCTION("""COMPUTED_VALUE"""),65) -> 65 | B66: =IFERROR(__xludf.DUMMYFUNCTION("""COMPUTED_VALUE"""),"Indore City") -> Indore City | C66: =IFERROR(__xludf.DUMMYFUNCTION("""COMPUTED_VALUE"""),"PRINCESS SHOPEE") -> PRINCESS SHOPEE | D66: =IFERROR(__xludf.DUMMYFUNCTION("""COMPUTED_VALUE"""),1699237877) -> 1699237877 | E66: =IFERROR(__xludf.DUMMYFUNCTION("""COMPUTED_VALUE"""),46232) -> 46232 | G66: =IFERROR(__xludf.DUMMYFUNCTION("""COMPUTED_VALUE"""),"B2C") -> B2C | H66: =IFERROR(__xludf.DUMMYFUNCTION("""COMPUTED_VALUE"""),"Jalaj Rawat") -> Jalaj Rawat
A67: =IFERROR(__xludf.DUMMYFUNCTION("""COMPUTED_VALUE"""),66) -> 66 | B67: =IFERROR(__xludf.DUMMYFUNCTION("""COMPUTED_VALUE"""),"Indore City") -> Indore City | C67: =IFERROR(__xludf.DUMMYFUNCTION("""COMPUTED_VALUE"""),"rajratan industries private limited") -> rajratan industries private limited | D67: =IFERROR(__xludf.DUMMYFUNCTION("""COMPUTED_VALUE"""),1223677972) -> 1223677972 | E67: =IFERROR(__xludf.DUMMYFUNCTION("""COMPUTED_VALUE"""),46232) -> 46232 | G67: =IFERROR(__xludf.DUMMYFUNCTION("""COMPUTED_VALUE"""),"B2C") -> B2C | H67: =IFERROR(__xludf.DUMMYFUNCTION("""COMPUTED_VALUE"""),"Zuber Ahmed Khan") -> Zuber Ahmed Khan
A68: =IFERROR(__xludf.DUMMYFUNCTION("""COMPUTED_VALUE"""),67) -> 67 | B68: =IFERROR(__xludf.DUMMYFUNCTION("""COMPUTED_VALUE"""),"Indore City") -> Indore City | C68: =IFERROR(__xludf.DUMMYFUNCTION("""COMPUTED_VALUE"""),"THE CRAFT SHELF") -> THE CRAFT SHELF | D68: =IFERROR(__xludf.DUMMYFUNCTION("""COMPUTED_VALUE"""),1997809878) -> 1997809878 | E68: =IFERROR(__xludf.DUMMYFUNCTION("""COMPUTED_VALUE"""),46232) -> 46232 | G68: =IFERROR(__xludf.DUMMYFUNCTION("""COMPUTED_VALUE"""),"B2C") -> B2C | H68: =IFERROR(__xludf.DUMMYFUNCTION("""COMPUTED_VALUE"""),"Zuber Ahmed Khan") -> Zuber Ahmed Khan
A69: =IFERROR(__xludf.DUMMYFUNCTION("""COMPUTED_VALUE"""),68) -> 68 | B69: =IFERROR(__xludf.DUMMYFUNCTION("""COMPUTED_VALUE"""),"Indore City") -> Indore City | C69: =IFERROR(__xludf.DUMMYFUNCTION("""COMPUTED_VALUE"""),"3A SERVICES") -> 3A SERVICES | D69: =IFERROR(__xludf.DUMMYFUNCTION("""COMPUTED_VALUE"""),1473198944) -> 1473198944 | E69: =IFERROR(__xludf.DUMMYFUNCTION("""COMPUTED_VALUE"""),46233) -> 46233 | G69: =IFERROR(__xludf.DUMMYFUNCTION("""COMPUTED_VALUE"""),"B2C") -> B2C | H69: =IFERROR(__xludf.DUMMYFUNCTION("""COMPUTED_VALUE"""),"Rahul Panchal") -> Rahul Panchal
A70: =IFERROR(__xludf.DUMMYFUNCTION("""COMPUTED_VALUE"""),69) -> 69 | B70: =IFERROR(__xludf.DUMMYFUNCTION("""COMPUTED_VALUE"""),"Indore City") -> Indore City | C70: =IFERROR(__xludf.DUMMYFUNCTION("""COMPUTED_VALUE"""),"SBI BANK AMCC BRANCH GPO CAMPUS") -> SBI BANK AMCC BRANCH GPO CAMPUS | D70: =IFERROR(__xludf.DUMMYFUNCTION("""COMPUTED_VALUE"""),1214563388) -> 1214563388 | E70: =IFERROR(__xludf.DUMMYFUNCTION("""COMPUTED_VALUE"""),46233) -> 46233 | G70: =IFERROR(__xludf.DUMMYFUNCTION("""COMPUTED_VALUE"""),"B2C") -> B2C | H70: =IFERROR(__xludf.DUMMYFUNCTION("""COMPUTED_VALUE"""),"Zuber Ahmed Khan") -> Zuber Ahmed Khan
A71: =IFERROR(__xludf.DUMMYFUNCTION("""COMPUTED_VALUE"""),70) -> 70 | B71: =IFERROR(__xludf.DUMMYFUNCTION("""COMPUTED_VALUE"""),"Indore City") -> Indore City | C71: =IFERROR(__xludf.DUMMYFUNCTION("""COMPUTED_VALUE"""),"G S MARKETING") -> G S MARKETING | D71: =IFERROR(__xludf.DUMMYFUNCTION("""COMPUTED_VALUE"""),1375646231) -> 1375646231 | E71: =IFERROR(__xludf.DUMMYFUNCTION("""COMPUTED_VALUE"""),46238) -> 46238 | G71: =IFERROR(__xludf.DUMMYFUNCTION("""COMPUTED_VALUE"""),"B2C") -> B2C | H71: =IFERROR(__xludf.DUMMYFUNCTION("""COMPUTED_VALUE"""),"Zuber Ahmed Khan") -> Zuber Ahmed Khan
A72: =IFERROR(__xludf.DUMMYFUNCTION("""COMPUTED_VALUE"""),71) -> 71 | B72: =IFERROR(__xludf.DUMMYFUNCTION("""COMPUTED_VALUE"""),"Indore City") -> Indore City | C72: =IFERROR(__xludf.DUMMYFUNCTION("""COMPUTED_VALUE"""),"JANA SMALL FINANCE BANK LIMITED") -> JANA SMALL FINANCE BANK LIMITED | D72: =IFERROR(__xludf.DUMMYFUNCTION("""COMPUTED_VALUE"""),1123451318) -> 1123451318 | E72: =IFERROR(__xludf.DUMMYFUNCTION("""COMPUTED_VALUE"""),46238) -> 46238 | G72: =IFERROR(__xludf.DUMMYFUNCTION("""COMPUTED_VALUE"""),"B2C") -> B2C | H72: =IFERROR(__xludf.DUMMYFUNCTION("""COMPUTED_VALUE"""),"Rahul Panchal") -> Rahul Panchal
A73: =IFERROR(__xludf.DUMMYFUNCTION("""COMPUTED_VALUE"""),72) -> 72 | B73: =IFERROR(__xludf.DUMMYFUNCTION("""COMPUTED_VALUE"""),"Indore City") -> Indore City | C73: =IFERROR(__xludf.DUMMYFUNCTION("""COMPUTED_VALUE"""),"sixth sense marketing pvt.ltd") -> sixth sense marketing pvt.ltd | D73: =IFERROR(__xludf.DUMMYFUNCTION("""COMPUTED_VALUE"""),1352121329) -> 1352121329 | E73: =IFERROR(__xludf.DUMMYFUNCTION("""COMPUTED_VALUE"""),46238) -> 46238 | G73: =IFERROR(__xludf.DUMMYFUNCTION("""COMPUTED_VALUE"""),"B2C") -> B2C | H73: =IFERROR(__xludf.DUMMYFUNCTION("""COMPUTED_VALUE"""),"Zuber Ahmed Khan") -> Zuber Ahmed Khan
A74: =IFERROR(__xludf.DUMMYFUNCTION("""COMPUTED_VALUE"""),73) -> 73 | B74: =IFERROR(__xludf.DUMMYFUNCTION("""COMPUTED_VALUE"""),"Indore City") -> Indore City | C74: =IFERROR(__xludf.DUMMYFUNCTION("""COMPUTED_VALUE"""),"AYODHYA PRAKASH AYURVEDA") -> AYODHYA PRAKASH AYURVEDA | D74: =IFERROR(__xludf.DUMMYFUNCTION("""COMPUTED_VALUE"""),3000069615) -> 3000069615 | E74: =IFERROR(__xludf.DUMMYFUNCTION("""COMPUTED_VALUE"""),46239) -> 46239 | G74: =IFERROR(__xludf.DUMMYFUNCTION("""COMPUTED_VALUE"""),"B2C") -> B2C | H74: =IFERROR(__xludf.DUMMYFUNCTION("""COMPUTED_VALUE"""),"Jalaj Rawat") -> Jalaj Rawat
A75: =IFERROR(__xludf.DUMMYFUNCTION("""COMPUTED_VALUE"""),74) -> 74 | B75: =IFERROR(__xludf.DUMMYFUNCTION("""COMPUTED_VALUE"""),"Indore City") -> Indore City | C75: =IFERROR(__xludf.DUMMYFUNCTION("""COMPUTED_VALUE"""),"DWIVEDI ENTERPRISES") -> DWIVEDI ENTERPRISES | D75: =IFERROR(__xludf.DUMMYFUNCTION("""COMPUTED_VALUE"""),1136441715) -> 1136441715 | E75: =IFERROR(__xludf.DUMMYFUNCTION("""COMPUTED_VALUE"""),46239) -> 46239 | G75: =IFERROR(__xludf.DUMMYFUNCTION("""COMPUTED_VALUE"""),"B2C") -> B2C | H75: =IFERROR(__xludf.DUMMYFUNCTION("""COMPUTED_VALUE"""),"Jalaj Rawat") -> Jalaj Rawat
A76: =IFERROR(__xludf.DUMMYFUNCTION("""COMPUTED_VALUE"""),75) -> 75 | B76: =IFERROR(__xludf.DUMMYFUNCTION("""COMPUTED_VALUE"""),"Indore City") -> Indore City | C76: =IFERROR(__xludf.DUMMYFUNCTION("""COMPUTED_VALUE"""),"IMPULSE AYURVEDA CARE") -> IMPULSE AYURVEDA CARE | D76: =IFERROR(__xludf.DUMMYFUNCTION("""COMPUTED_VALUE"""),1659043732) -> 1659043732 | E76: =IFERROR(__xludf.DUMMYFUNCTION("""COMPUTED_VALUE"""),46239) -> 46239 | G76: =IFERROR(__xludf.DUMMYFUNCTION("""COMPUTED_VALUE"""),"B2C") -> B2C | H76: =IFERROR(__xludf.DUMMYFUNCTION("""COMPUTED_VALUE"""),"Jalaj Rawat") -> Jalaj Rawat
A77: =IFERROR(__xludf.DUMMYFUNCTION("""COMPUTED_VALUE"""),76) -> 76 | B77: =IFERROR(__xludf.DUMMYFUNCTION("""COMPUTED_VALUE"""),"Indore City") -> Indore City | C77: =IFERROR(__xludf.DUMMYFUNCTION("""COMPUTED_VALUE"""),"krishi darshan and company") -> krishi darshan and company | D77: =IFERROR(__xludf.DUMMYFUNCTION("""COMPUTED_VALUE"""),1961828217) -> 1961828217 | E77: =IFERROR(__xludf.DUMMYFUNCTION("""COMPUTED_VALUE"""),46239) -> 46239 | G77: =IFERROR(__xludf.DUMMYFUNCTION("""COMPUTED_VALUE"""),"B2C") -> B2C | H77: =IFERROR(__xludf.DUMMYFUNCTION("""COMPUTED_VALUE"""),"Zuber Ahmed Khan") -> Zuber Ahmed Khan
A78: =IFERROR(__xludf.DUMMYFUNCTION("""COMPUTED_VALUE"""),77) -> 77 | B78: =IFERROR(__xludf.DUMMYFUNCTION("""COMPUTED_VALUE"""),"Indore City") -> Indore City | C78: =IFERROR(__xludf.DUMMYFUNCTION("""COMPUTED_VALUE"""),"MAA FALAUDI DISTRIBUTERS") -> MAA FALAUDI DISTRIBUTERS | D78: =IFERROR(__xludf.DUMMYFUNCTION("""COMPUTED_VALUE"""),3000066866) -> 3000066866 | E78: =IFERROR(__xludf.DUMMYFUNCTION("""COMPUTED_VALUE"""),46239) -> 46239 | G78: =IFERROR(__xludf.DUMMYFUNCTION("""COMPUTED_VALUE"""),"B2C") -> B2C | H78: =IFERROR(__xludf.DUMMYFUNCTION("""COMPUTED_VALUE"""),"Jalaj Rawat") -> Jalaj Rawat
A79: =IFERROR(__xludf.DUMMYFUNCTION("""COMPUTED_VALUE"""),78) -> 78 | B79: =IFERROR(__xludf.DUMMYFUNCTION("""COMPUTED_VALUE"""),"Indore City") -> Indore City | C79: =IFERROR(__xludf.DUMMYFUNCTION("""COMPUTED_VALUE"""),"MASTER MIND BOOK") -> MASTER MIND BOOK | D79: =IFERROR(__xludf.DUMMYFUNCTION("""COMPUTED_VALUE"""),1190143405) -> 1190143405 | E79: =IFERROR(__xludf.DUMMYFUNCTION("""COMPUTED_VALUE"""),46239) -> 46239 | G79: =IFERROR(__xludf.DUMMYFUNCTION("""COMPUTED_VALUE"""),"B2C") -> B2C | H79: =IFERROR(__xludf.DUMMYFUNCTION("""COMPUTED_VALUE"""),"Rahul Panchal") -> Rahul Panchal
A80: =IFERROR(__xludf.DUMMYFUNCTION("""COMPUTED_VALUE"""),79) -> 79 | B80: =IFERROR(__xludf.DUMMYFUNCTION("""COMPUTED_VALUE"""),"Indore City") -> Indore City | C80: =IFERROR(__xludf.DUMMYFUNCTION("""COMPUTED_VALUE"""),"NARAYANA FOODS") -> NARAYANA FOODS | D80: =IFERROR(__xludf.DUMMYFUNCTION("""COMPUTED_VALUE"""),1577251666) -> 1577251666 | E80: =IFERROR(__xludf.DUMMYFUNCTION("""COMPUTED_VALUE"""),46239) -> 46239 | G80: =IFERROR(__xludf.DUMMYFUNCTION("""COMPUTED_VALUE"""),"B2C") -> B2C | H80: =IFERROR(__xludf.DUMMYFUNCTION("""COMPUTED_VALUE"""),"Jalaj Rawat") -> Jalaj Rawat
A81: =IFERROR(__xludf.DUMMYFUNCTION("""COMPUTED_VALUE"""),80) -> 80 | B81: =IFERROR(__xludf.DUMMYFUNCTION("""COMPUTED_VALUE"""),"Indore City") -> Indore City | C81: =IFERROR(__xludf.DUMMYFUNCTION("""COMPUTED_VALUE"""),"BALAJI EXPRESS SERVICE") -> BALAJI EXPRESS SERVICE | D81: =IFERROR(__xludf.DUMMYFUNCTION("""COMPUTED_VALUE"""),1682921625) -> 1682921625 | E81: =IFERROR(__xludf.DUMMYFUNCTION("""COMPUTED_VALUE"""),46241) -> 46241 | G81: =IFERROR(__xludf.DUMMYFUNCTION("""COMPUTED_VALUE"""),"B2C") -> B2C | H81: =IFERROR(__xludf.DUMMYFUNCTION("""COMPUTED_VALUE"""),"Zuber Ahmed Khan") -> Zuber Ahmed Khan
A82: =IFERROR(__xludf.DUMMYFUNCTION("""COMPUTED_VALUE"""),81) -> 81 | B82: =IFERROR(__xludf.DUMMYFUNCTION("""COMPUTED_VALUE"""),"Indore City") -> Indore City | C82: =IFERROR(__xludf.DUMMYFUNCTION("""COMPUTED_VALUE"""),"HIMANSHU TRADERS") -> HIMANSHU TRADERS | D82: =IFERROR(__xludf.DUMMYFUNCTION("""COMPUTED_VALUE"""),1658779587) -> 1658779587 | E82: =IFERROR(__xludf.DUMMYFUNCTION("""COMPUTED_VALUE"""),46241) -> 46241 | G82: =IFERROR(__xludf.DUMMYFUNCTION("""COMPUTED_VALUE"""),"B2C") -> B2C | H82: =IFERROR(__xludf.DUMMYFUNCTION("""COMPUTED_VALUE"""),"Zuber Ahmed Khan") -> Zuber Ahmed Khan
A83: =IFERROR(__xludf.DUMMYFUNCTION("""COMPUTED_VALUE"""),82) -> 82 | B83: =IFERROR(__xludf.DUMMYFUNCTION("""COMPUTED_VALUE"""),"Indore City") -> Indore City | C83: =IFERROR(__xludf.DUMMYFUNCTION("""COMPUTED_VALUE"""),"LUCKYS PHARMA LAB PVT LTD") -> LUCKYS PHARMA LAB PVT LTD | D83: =IFERROR(__xludf.DUMMYFUNCTION("""COMPUTED_VALUE"""),1684392997) -> 1684392997 | E83: =IFERROR(__xludf.DUMMYFUNCTION("""COMPUTED_VALUE"""),46241) -> 46241 | G83: =IFERROR(__xludf.DUMMYFUNCTION("""COMPUTED_VALUE"""),"B2C") -> B2C | H83: =IFERROR(__xludf.DUMMYFUNCTION("""COMPUTED_VALUE"""),"Jalaj Rawat") -> Jalaj Rawat
A84: =IFERROR(__xludf.DUMMYFUNCTION("""COMPUTED_VALUE"""),83) -> 83 | B84: =IFERROR(__xludf.DUMMYFUNCTION("""COMPUTED_VALUE"""),"Indore City") -> Indore City | C84: =IFERROR(__xludf.DUMMYFUNCTION("""COMPUTED_VALUE"""),"m.p. exam academy") -> m.p. exam academy | D84: =IFERROR(__xludf.DUMMYFUNCTION("""COMPUTED_VALUE"""),1774327470) -> 1774327470 | E84: =IFERROR(__xludf.DUMMYFUNCTION("""COMPUTED_VALUE"""),46241) -> 46241 | G84: =IFERROR(__xludf.DUMMYFUNCTION("""COMPUTED_VALUE"""),"B2C") -> B2C | H84: =IFERROR(__xludf.DUMMYFUNCTION("""COMPUTED_VALUE"""),"Rahul Panchal") -> Rahul Panchal
A85: =IFERROR(__xludf.DUMMYFUNCTION("""COMPUTED_VALUE"""),84) -> 84 | B85: =IFERROR(__xludf.DUMMYFUNCTION("""COMPUTED_VALUE"""),"Indore City") -> Indore City | C85: =IFERROR(__xludf.DUMMYFUNCTION("""COMPUTED_VALUE"""),"sansaram") -> sansaram | D85: =IFERROR(__xludf.DUMMYFUNCTION("""COMPUTED_VALUE"""),1274236974) -> 1274236974 | E85: =IFERROR(__xludf.DUMMYFUNCTION("""COMPUTED_VALUE"""),46241) -> 46241 | G85: =IFERROR(__xludf.DUMMYFUNCTION("""COMPUTED_VALUE"""),"B2C") -> B2C | H85: =IFERROR(__xludf.DUMMYFUNCTION("""COMPUTED_VALUE"""),"Rahul Panchal") -> Rahul Panchal
A86: =IFERROR(__xludf.DUMMYFUNCTION("""COMPUTED_VALUE"""),85) -> 85 | B86: =IFERROR(__xludf.DUMMYFUNCTION("""COMPUTED_VALUE"""),"Indore City") -> Indore City | C86: =IFERROR(__xludf.DUMMYFUNCTION("""COMPUTED_VALUE"""),"shri satyasai books and publication trust") -> shri satyasai books and publication trust | D86: =IFERROR(__xludf.DUMMYFUNCTION("""COMPUTED_VALUE"""),1685737865) -> 1685737865 | E86: =IFERROR(__xludf.DUMMYFUNCTION("""COMPUTED_VALUE"""),46241) -> 46241 | G86: =IFERROR(__xludf.DUMMYFUNCTION("""COMPUTED_VALUE"""),"B2C") -> B2C | H86: =IFERROR(__xludf.DUMMYFUNCTION("""COMPUTED_VALUE"""),"Zuber Ahmed Khan") -> Zuber Ahmed Khan
A87: =IFERROR(__xludf.DUMMYFUNCTION("""COMPUTED_VALUE"""),86) -> 86 | B87: =IFERROR(__xludf.DUMMYFUNCTION("""COMPUTED_VALUE"""),"Indore City") -> Indore City | C87: =IFERROR(__xludf.DUMMYFUNCTION("""COMPUTED_VALUE"""),"SYNERGY VENTURES") -> SYNERGY VENTURES | D87: =IFERROR(__xludf.DUMMYFUNCTION("""COMPUTED_VALUE"""),1725308207) -> 1725308207 | E87: =IFERROR(__xludf.DUMMYFUNCTION("""COMPUTED_VALUE"""),46241) -> 46241 | G87: =IFERROR(__xludf.DUMMYFUNCTION("""COMPUTED_VALUE"""),"B2C") -> B2C | H87: =IFERROR(__xludf.DUMMYFUNCTION("""COMPUTED_VALUE"""),"Zuber Ahmed Khan") -> Zuber Ahmed Khan
A88: =IFERROR(__xludf.DUMMYFUNCTION("""COMPUTED_VALUE"""),87) -> 87 | B88: =IFERROR(__xludf.DUMMYFUNCTION("""COMPUTED_VALUE"""),"Indore City") -> Indore City | C88: =IFERROR(__xludf.DUMMYFUNCTION("""COMPUTED_VALUE"""),"the word among us") -> the word among us | D88: =IFERROR(__xludf.DUMMYFUNCTION("""COMPUTED_VALUE"""),1445096237) -> 1445096237 | E88: =IFERROR(__xludf.DUMMYFUNCTION("""COMPUTED_VALUE"""),46241) -> 46241 | G88: =IFERROR(__xludf.DUMMYFUNCTION("""COMPUTED_VALUE"""),"B2C") -> B2C | H88: =IFERROR(__xludf.DUMMYFUNCTION("""COMPUTED_VALUE"""),"Rahul Panchal") -> Rahul Panchal
A89: =IFERROR(__xludf.DUMMYFUNCTION("""COMPUTED_VALUE"""),88) -> 88 | B89: =IFERROR(__xludf.DUMMYFUNCTION("""COMPUTED_VALUE"""),"Indore City") -> Indore City | C89: =IFERROR(__xludf.DUMMYFUNCTION("""COMPUTED_VALUE"""),"YUMILOOP") -> YUMILOOP | D89: =IFERROR(__xludf.DUMMYFUNCTION("""COMPUTED_VALUE"""),1676380595) -> 1676380595 | E89: =IFERROR(__xludf.DUMMYFUNCTION("""COMPUTED_VALUE"""),46241) -> 46241 | G89: =IFERROR(__xludf.DUMMYFUNCTION("""COMPUTED_VALUE"""),"B2C") -> B2C | H89: =IFERROR(__xludf.DUMMYFUNCTION("""COMPUTED_VALUE"""),"Jalaj Rawat") -> Jalaj Rawat
A90: =IFERROR(__xludf.DUMMYFUNCTION("""COMPUTED_VALUE"""),89) -> 89 | B90: =IFERROR(__xludf.DUMMYFUNCTION("""COMPUTED_VALUE"""),"Indore City") -> Indore City | C90: =IFERROR(__xludf.DUMMYFUNCTION("""COMPUTED_VALUE"""),"golden fortune") -> golden fortune | D90: =IFERROR(__xludf.DUMMYFUNCTION("""COMPUTED_VALUE"""),1733415161) -> 1733415161 | E90: =IFERROR(__xludf.DUMMYFUNCTION("""COMPUTED_VALUE"""),46244) -> 46244 | G90: =IFERROR(__xludf.DUMMYFUNCTION("""COMPUTED_VALUE"""),"B2C") -> B2C | H90: =IFERROR(__xludf.DUMMYFUNCTION("""COMPUTED_VALUE"""),"Rahul Panchal") -> Rahul Panchal
A91: =IFERROR(__xludf.DUMMYFUNCTION("""COMPUTED_VALUE"""),90) -> 90 | B91: =IFERROR(__xludf.DUMMYFUNCTION("""COMPUTED_VALUE"""),"Indore City") -> Indore City | C91: =IFERROR(__xludf.DUMMYFUNCTION("""COMPUTED_VALUE"""),"KRATI ENTERPRISES") -> KRATI ENTERPRISES | D91: =IFERROR(__xludf.DUMMYFUNCTION("""COMPUTED_VALUE"""),1350549684) -> 1350549684 | E91: =IFERROR(__xludf.DUMMYFUNCTION("""COMPUTED_VALUE"""),46244) -> 46244 | G91: =IFERROR(__xludf.DUMMYFUNCTION("""COMPUTED_VALUE"""),"B2C") -> B2C | H91: =IFERROR(__xludf.DUMMYFUNCTION("""COMPUTED_VALUE"""),"Zuber Ahmed Khan") -> Zuber Ahmed Khan
A92: =IFERROR(__xludf.DUMMYFUNCTION("""COMPUTED_VALUE"""),91) -> 91 | B92: =IFERROR(__xludf.DUMMYFUNCTION("""COMPUTED_VALUE"""),"Indore City") -> Indore City | C92: =IFERROR(__xludf.DUMMYFUNCTION("""COMPUTED_VALUE"""),"madhav overses corporation") -> madhav overses corporation | D92: =IFERROR(__xludf.DUMMYFUNCTION("""COMPUTED_VALUE"""),1813348405) -> 1813348405 | E92: =IFERROR(__xludf.DUMMYFUNCTION("""COMPUTED_VALUE"""),46244) -> 46244 | G92: =IFERROR(__xludf.DUMMYFUNCTION("""COMPUTED_VALUE"""),"B2C") -> B2C | H92: =IFERROR(__xludf.DUMMYFUNCTION("""COMPUTED_VALUE"""),"Rahul Panchal") -> Rahul Panchal
A93: =IFERROR(__xludf.DUMMYFUNCTION("""COMPUTED_VALUE"""),92) -> 92 | B93: =IFERROR(__xludf.DUMMYFUNCTION("""COMPUTED_VALUE"""),"Indore City") -> Indore City | C93: =IFERROR(__xludf.DUMMYFUNCTION("""COMPUTED_VALUE"""),"shreeji collection") -> shreeji collection | D93: =IFERROR(__xludf.DUMMYFUNCTION("""COMPUTED_VALUE"""),1938121786) -> 1938121786 | E93: =IFERROR(__xludf.DUMMYFUNCTION("""COMPUTED_VALUE"""),46244) -> 46244 | G93: =IFERROR(__xludf.DUMMYFUNCTION("""COMPUTED_VALUE"""),"B2C") -> B2C | H93: =IFERROR(__xludf.DUMMYFUNCTION("""COMPUTED_VALUE"""),"Jalaj Rawat") -> Jalaj Rawat
A94: =IFERROR(__xludf.DUMMYFUNCTION("""COMPUTED_VALUE"""),93) -> 93 | B94: =IFERROR(__xludf.DUMMYFUNCTION("""COMPUTED_VALUE"""),"Indore City") -> Indore City | C94: =IFERROR(__xludf.DUMMYFUNCTION("""COMPUTED_VALUE"""),"The Ayurveda Hub Healthcare Pvt Ltd") -> The Ayurveda Hub Healthcare Pvt Ltd | D94: =IFERROR(__xludf.DUMMYFUNCTION("""COMPUTED_VALUE"""),1253677581) -> 1253677581 | E94: =IFERROR(__xludf.DUMMYFUNCTION("""COMPUTED_VALUE"""),46244) -> 46244 | G94: =IFERROR(__xludf.DUMMYFUNCTION("""COMPUTED_VALUE"""),"B2C") -> B2C | H94: =IFERROR(__xludf.DUMMYFUNCTION("""COMPUTED_VALUE"""),"Jalaj Rawat") -> Jalaj Rawat
A95: =IFERROR(__xludf.DUMMYFUNCTION("""COMPUTED_VALUE"""),94) -> 94 | B95: =IFERROR(__xludf.DUMMYFUNCTION("""COMPUTED_VALUE"""),"Indore City") -> Indore City | C95: =IFERROR(__xludf.DUMMYFUNCTION("""COMPUTED_VALUE"""),"KD SHOPING") -> KD SHOPING | D95: =IFERROR(__xludf.DUMMYFUNCTION("""COMPUTED_VALUE"""),1725852955) -> 1725852955 | E95: =IFERROR(__xludf.DUMMYFUNCTION("""COMPUTED_VALUE"""),46246) -> 46246 | G95: =IFERROR(__xludf.DUMMYFUNCTION("""COMPUTED_VALUE"""),"B2C") -> B2C | H95: =IFERROR(__xludf.DUMMYFUNCTION("""COMPUTED_VALUE"""),"Jalaj Rawat") -> Jalaj Rawat
A96: =IFERROR(__xludf.DUMMYFUNCTION("""COMPUTED_VALUE"""),95) -> 95 | B96: =IFERROR(__xludf.DUMMYFUNCTION("""COMPUTED_VALUE"""),"Indore City") -> Indore City | C96: =IFERROR(__xludf.DUMMYFUNCTION("""COMPUTED_VALUE"""),"MYSHA CREATION") -> MYSHA CREATION | D96: =IFERROR(__xludf.DUMMYFUNCTION("""COMPUTED_VALUE"""),3000067733) -> 3000067733 | E96: =IFERROR(__xludf.DUMMYFUNCTION("""COMPUTED_VALUE"""),46246) -> 46246 | G96: =IFERROR(__xludf.DUMMYFUNCTION("""COMPUTED_VALUE"""),"B2C") -> B2C | H96: =IFERROR(__xludf.DUMMYFUNCTION("""COMPUTED_VALUE"""),"Jalaj Rawat") -> Jalaj Rawat
A97: =IFERROR(__xludf.DUMMYFUNCTION("""COMPUTED_VALUE"""),96) -> 96 | B97: =IFERROR(__xludf.DUMMYFUNCTION("""COMPUTED_VALUE"""),"Indore City") -> Indore City | C97: =IFERROR(__xludf.DUMMYFUNCTION("""COMPUTED_VALUE"""),"SANDESH YARN TRDING COMPANY PRIVATE LIMITED") -> SANDESH YARN TRDING COMPANY PRIVATE LIMITED | D97: =IFERROR(__xludf.DUMMYFUNCTION("""COMPUTED_VALUE"""),1762979652) -> 1762979652 | E97: =IFERROR(__xludf.DUMMYFUNCTION("""COMPUTED_VALUE"""),46246) -> 46246 | G97: =IFERROR(__xludf.DUMMYFUNCTION("""COMPUTED_VALUE"""),"B2C") -> B2C | H97: =IFERROR(__xludf.DUMMYFUNCTION("""COMPUTED_VALUE"""),"Rahul Panchal") -> Rahul Panchal
A98: =IFERROR(__xludf.DUMMYFUNCTION("""COMPUTED_VALUE"""),97) -> 97 | B98: =IFERROR(__xludf.DUMMYFUNCTION("""COMPUTED_VALUE"""),"Indore City") -> Indore City | C98: =IFERROR(__xludf.DUMMYFUNCTION("""COMPUTED_VALUE"""),"THE CURRENCYPEDIA") -> THE CURRENCYPEDIA | D98: =IFERROR(__xludf.DUMMYFUNCTION("""COMPUTED_VALUE"""),3000063279) -> 3000063279 | E98: =IFERROR(__xludf.DUMMYFUNCTION("""COMPUTED_VALUE"""),46246) -> 46246 | G98: =IFERROR(__xludf.DUMMYFUNCTION("""COMPUTED_VALUE"""),"B2C") -> B2C | H98: =IFERROR(__xludf.DUMMYFUNCTION("""COMPUTED_VALUE"""),"Jalaj Rawat") -> Jalaj Rawat
A99: =IFERROR(__xludf.DUMMYFUNCTION("""COMPUTED_VALUE"""),98) -> 98 | B99: =IFERROR(__xludf.DUMMYFUNCTION("""COMPUTED_VALUE"""),"Indore City") -> Indore City | C99: =IFERROR(__xludf.DUMMYFUNCTION("""COMPUTED_VALUE"""),"White O Splash") -> White O Splash | D99: =IFERROR(__xludf.DUMMYFUNCTION("""COMPUTED_VALUE"""),1730557738) -> 1730557738 | E99: =IFERROR(__xludf.DUMMYFUNCTION("""COMPUTED_VALUE"""),46246) -> 46246 | G99: =IFERROR(__xludf.DUMMYFUNCTION("""COMPUTED_VALUE"""),"B2C") -> B2C | H99: =IFERROR(__xludf.DUMMYFUNCTION("""COMPUTED_VALUE"""),"Jalaj Rawat") -> Jalaj Rawat
A100: =IFERROR(__xludf.DUMMYFUNCTION("""COMPUTED_VALUE"""),99) -> 99 | B100: =IFERROR(__xludf.DUMMYFUNCTION("""COMPUTED_VALUE"""),"Indore City") -> Indore City | C100: =IFERROR(__xludf.DUMMYFUNCTION("""COMPUTED_VALUE"""),"CUNTZTHRIFT") -> CUNTZTHRIFT | D100: =IFERROR(__xludf.DUMMYFUNCTION("""COMPUTED_VALUE"""),1622015534) -> 1622015534 | E100: =IFERROR(__xludf.DUMMYFUNCTION("""COMPUTED_VALUE"""),46248) -> 46248 | G100: =IFERROR(__xludf.DUMMYFUNCTION("""COMPUTED_VALUE"""),"B2C") -> B2C | H100: =IFERROR(__xludf.DUMMYFUNCTION("""COMPUTED_VALUE"""),"Rahul Panchal") -> Rahul Panchal
...

Sheet Indore City
F2: From Date 01.04.2026 to 31.08.2026
B3: S.No. | C3: Division | D3: Name of Customer | E3: Customer ID | F3: Date of Onboarding | G3: Product Type | H3: B2B Or B2C | I3: Name of ME Who Onboarded | J3: Customer Type Advance/ BNPL
B4: 1 | C4: Indore City | D4: DRASHTI ENTERPRISES | E4: 1504860613 | F4: 46114 | H4: B2C | I4: Jalaj Rawat
B5: 2 | C5: Indore City | D5: PRIYAL AQUATECH SERVICES | E5: 1893026504 | F5: 46114 | H5: B2C | I5: Jalaj Rawat
B6: 3 | C6: Indore City | D6: VARNSHIKA HERBALS PVT LTD | E6: 1149636129 | F6: 46114 | H6: B2C | I6: Rahul Panchal
B7: 4 | C7: Indore City | D7: SANWARIYA HERBALS | E7: 1858516980 | F7: 46119 | H7: B2C | I7: Jalaj Rawat
B8: 5 | C8: Indore City | D8: Bank of India zonal office indore | E8: 1540291063 | F8: 46121 | H8: B2C | I8: Jalaj Rawat
B9: 6 | C9: Indore City | D9: SWARAJ COACHING CLASSES | E9: 1601260495 | F9: 46121 | H9: B2C | I9: Zuber Ahmed Khan
B10: 7 | C10: Indore City | D10: MPPKVVCL | E10: 1955152285 | F10: 46127 | H10: B2C | I10: Rahul Panchal
B11: 8 | C11: Indore City | D11: RSP ENTERPRISES | E11: 1784698475 | F11: 46127 | H11: B2C | I11: Jalaj Rawat
B12: 9 | C12: Indore City | D12: SP WORLD SOLUTION | E12: 1802814193 | F12: 46127 | H12: B2C | I12: Jalaj Rawat
B13: 10 | C13: Indore City | D13: ASHU HERBAL | E13: 1264378880 | F13: 46128 | H13: B2C | I13: Zuber Ahmed Khan
B14: 11 | C14: Indore City | D14: JAIN ENTERPRISES | E14: 1244430040 | F14: 46136 | H14: B2C | I14: Jalaj Rawat
B15: 12 | C15: Indore City | D15: LASNARO AGROVET PRIVATE LIMITED | E15: 1335697406 | F15: 46136 | H15: B2C | I15: Rahul Panchal
... B147: 144 | C147: Indore City | D147: SDJ ENTERPRISES | E147: 1834308501 | F147: 46294 | H147: B2C | I147: Jalaj Rawat

Sheet Indore MFL
F2: From Date 01.04.2026 to 31.08.2026
B3: S.No. | C3: Division | D3: Name of Customer | E3: Customer ID | F3: Date of Onboarding | G3: Product Type | H3: B2B Or B2C | I3: Name of ME Who Onboarded | J3: Customer Type Advance/ BNPL
B4: 1 | C4: Indore MFL | D4: SBI AMCC DEWAS | E4: 1143151756 | F4: 46251 | G4: LETTERS | H4: B2C | I4: SANTOSH VERMA | J4: BNPL
B5: 2 | C5: Indore MFL | D5: GURUKRIPA FOODS | E5: 1724127341 | F5: 46248 | G5: FMCG | H5: B2C | I5: BRIJESH SHRIVAS | J5: ADVANCE
B6: 3 | C6: Indore MFL | D6: KASHISH SAREE | E6: 1176938537 | F6: 46246 | G6: FASHION | H6: B2C | I6: SANTOSH VERMA | J6: ADVANCE
B7: 4 | C7: Indore MFL | D7: SA HERBAL BIOACTIVE LLP | E7: 1646616392 | F7: 46246 | G7: HERBVAL PRODUCTS | H7: B2C | I7: BRIJESH SHRIVAS | J7: ADVANCE
B8: 5 | C8: Indore MFL | D8: BHUMI AGRO INDUSTRIES | E8: 1761937114 | F8: 46239 | G8: LETTERS | H8: B2C | I8: SANTOSH VERMA | J8: ADVANCE
B9: 6 | C9: Indore MFL | D9: CENTRAL BANK OF INDIA | E9: 1512057439 | F9: 46232 | G9: HERBVAL PRODUCTS | H9: B2C | I9: BRIJESH SHRIVAS | J9: BNPL
B10: 7 | C10: Indore MFL | D10: BHUMI AGRO INDUSTRIES | E10: 1761937114 | F10: 46226 | G10: MEDICINES | H10: B2C | I10: SANTOSH VERMA | J10: ADVANCE
B11: 8 | C11: Indore MFL | D11: GOVIRA | E11: 1495342035 | F11: 46221 | G11: LETTERS | H11: B2C | I11: SANTOSH VERMA | J11: ADVANCE
B12: 9 | C12: Indore MFL | D12: state bank of india | E12: 1638295373 | F12: 46220 | G12: LETTERS | H12: B2C | I12: BRIJESH SHRIVAS | J12: BNPL
B13: 10 | C13: Indore MFL | D13: INNOVATIVE ENTERPRISES | E13: 1819752277 | F13: 46203 | G13: SPORTS PRODUCTS | H13: B2C | I13: SANTOSH VERMA | J13: ADVANCE
B14: 11 | C14: Indore MFL | D14: Rahul Khichi | E14: 1304572708 | F14: 46197 | G14: MACHINE GOODS | H14: B2C | I14: SANTOSH VERMA | J14: ADVANCE
B15: 12 | C15: Indore MFL | D15: LIC OF INDIA | E15: 1926099029 | F15: 46192 | G15: LETTERS | H15: B2C | I15: BRIJESH SHRIVAS | J15: BNPL
... B30: 27 | C30: Indore MFL | D30: IPPB Dewas | E30: 1973617996 | F30: 46266 | G30: LETTERS | H30: B2C | I30: SANTOSH VERMA | J30: BNPL

Sheet Khandwa
F2: From Date 01.04.2026 to 31.08.2026
B3: S.No. | C3: Division | D3: Name of Customer | E3: Customer ID | F3: Date of Onboarding | G3: Product Type | H3: B2B Or B2C | I3: Name of ME Who Onboarded | J3: Customer Type Advance/ BNPL
B4: 1 | C4: Khandwa | D4: PIONEER HANDLOOM | E4: 1599830445 | F4: 24.08.2026 | G4: Speed Post Parcel Domestic | H4: B2C | I4: VINEET PATEL | J4: ADVANCE
B5: 2 | C5: Khandwa | D5: SHIVRAM BILLORE | E5: 1433891952 | F5: 21.08.2026 | G5: Speed Post Parcel Domestic | H5: B2C | I5: VINEET PATEL | J5: ADVANCE
B6: 3 | C6: Khandwa | D6: BHAGYASHREE AGRAWAL | E6: 1147531131 | F6: 21.08.2026 | G6: Indiapost Parcel Contractual | H6: B2C | I6: junaid khan | J6: ADVANCE
B7: 4 | C7: Khandwa | D7: New Kanpur Chappal Sale | E7: 1438989417 | F7: 20.08.2026 | G7: Indiapost Parcel Contractual | H7: B2C | I7: VINEET PATEL | J7: ADVANCE
B8: 5 | C8: Khandwa | D8: AKHTAR KHAN | E8: 1896217385 | F8: 17.08.2026 | G8: Indiapost Parcel Contractual | H8: B2C | I8: junaid khan | J8: ADVANCE
B9: 6 | C9: Khandwa | D9: YASHWANT MANGOLIYA | E9: 1582492512 | F9: 17.08.2026 | G9: Indiapost Parcel Contractual | H9: B2C | I9: VINEET PATEL | J9: ADVANCE
B10: 7 | C10: Khandwa | D10: MISS CHORCHET | E10: 1000058530 | F10: 17.08.2026 | G10: Indiapost Parcel Contractual | H10: B2C | I10: Sunil bhojwani | J10: ADVANCE
B11: 8 | C11: Khandwa | D11: MAHAK ASWANI | E11: 1509137621 | F11: 17.08.2026 | G11: Indiapost Parcel Contractual | H11: B2C | I11: junaid khan | J11: ADVANCE
B12: 9 | C12: Khandwa | D12: Khushi Shoes house | E12: 1454741637 | F12: 17.08.2026 | G12: Speed Post Parcel Domestic | H12: B2C | I12: VINEET PATEL | J12: ADVANCE
B13: 10 | C13: Khandwa | D13: AALI QADAR CLOTH STORES AND GENTS TAILORS | E13: 1849113146 | F13: 12.08.2026 | G13: Speed Post Parcel Domestic | H13: B2C | I13: Sunil bhojwani | J13: ADVANCE
B14: 11 | C14: Khandwa | D14: JITENDRA SISODIYA | E14: 1275942889 | F14: 12.08.2026 | G14: Speed Post Parcel Domestic | H14: B2C | I14: VINEET PATEL | J14: ADVANCE
B15: 12 | C15: Khandwa | D15: S M VILLAGE ENTERPRISE | E15: 1000058717 | F15: 17.08.2026 | G15: Indiapost Parcel Contractual | H15: B2C | I15: VINEET PATEL | J15: ADVANCE
... B64: 61 | C64: Khandwa | D64: SANJIVANI | E64: 1102887727 | F64: 08.09.2026 | G64: Speed Post Parcel Domestic | H64: B2C | I64: junaid khan | J64: ADVANCE
B65: 62 | C65: Khandwa | D65: DIDI NIGHT WEAR | E65: 1671108458 | F65: 08.09.2026 | G65: Indiapost Parcel Contractual | H65: B2C | J65: ADVANCE
B66: 63 | C66: Khandwa | D66: AYAJ KHAN | E66: 1621303953 | F66: 08.09.2026 | G66: Speed Post Parcel Domestic | H66: B2C | I66: sunil bhojwani | J66: ADVANCE
B67: 64 | C67: Khandwa | D67: AHSAAN ZAHEER QURESHI | E67: 1554947937 | F67: 08.09.2026 | G67: Speed Post Parcel Domestic | H67: B2C | J67: ADVANCE
B68: 65 | C68: Khandwa | D68: SHYAM SPARES | E68: 1916717972 | F68: 07.09.2026 | G68: Indiapost Parcel Contractual | H68: B2C | I68: sunil bhojwani | J68: ADVANCE
B69: 66 | C69: Khandwa | D69: Sanjay Gulya | E69: 1599377003 | F69: 07.09.2026 | G69: Speed Post Parcel Domestic | H69: B2C | I69: Vineet Patel | J69: ADVANCE
B70: 67 | C70: Khandwa | D70: Pankaj kewat | E70: 1311051856 | F70: 07.09.2026 | G70: Speed Post Parcel Domestic | H70: B2C | I70: vineet patel | J70: ADVANCE
B71: 68 | C71: Khandwa | D71: MISHRILAL VERMA | E71: 1707389443 | F71: 03.09.2026 | G71: Speed Post Parcel Domestic | H71: B2C | I71: vineet patel | J71: ADVANCE
B72: 69 | C72: Khandwa | D72: NAVKAR SAREE EMPORIUM | E72: 1369280565 | F72: 03.09.2026 | G72: Speed Post Parcel Domestic | H72: B2C | I72: santosh rathore | J72: ADVANCE
B73: 70 | C73: Khandwa | D73: NARENDRA JAISWAL | E73: 1408974164 | F73: 03.09.2026 | G73: Speed Post Parcel Domestic | H73: B2C | J73: ADVANCE
B74: 71 | C74: Khandwa | D74: RAVINDRA VERMA | E74: 1787286135 | F74: 03.09.2026 | G74: Speed Post Parcel Domestic | H74: B2C | I74: vineet patel | J74: ADVANCE
B75: 72 | C75: Khandwa | D75: SHIV NARMADESHWAR SHIVLING | E75: 1670881656 | F75: 03.09.2026 | G75: Speed Post Parcel Domestic | H75: B2C | I75: vineet patel | J75: ADVANCE
B76: 73 | C76: Khandwa | D76: Rahul | E76: 1820439245 | F76: 03.09.2026 | G76: Speed Post Parcel Domestic | H76: B2C | I76: vineet Patel | J76: ADVANCE
B77: 74 | C77: Khandwa | D77: SANJAY VERMA | E77: 1676340146 | F77: 03.09.2026 | G77: Speed Post Parcel Domestic | H77: B2C | J77: ADVANCE

Sheet Mandsaur
F2: From Date 01.04.2026 to 31.08.2026
B3: S.No. | C3: Division | D3: Name of Customer | E3: Customer ID | F3: Date of Onboarding | G3: Product Type | H3: B2B Or B2C | I3: Name of ME Who Onboarded | J3: Customer Type Advance/ BNPL
B4: 1 | C4: Mandsaur | D4: THE GLOBUS SHOES | E4: 1608065160 | F4: 46121 | H4: B2C | I4: Shri Yash Mittal | J4: Advance
B5: 2 | C5: Mandsaur | D5: shree shyam agro international | E5: 1750186689 | F5: 46125 | H5: B2C | I5: Shri Yash Mittal | J5: Advance
B6: 3 | C6: Mandsaur | D6: JAI AMBE AGRO | E6: 1109522542 | F6: 46137 | H6: B2C | I6: Shri Yash Mittal | J6: Advance
B7: 4 | C7: Mandsaur | D7: D COLLECTION | E7: 1811297002 | F7: 46141 | H7: B2C | I7: Shri Yash Mittal | J7: Advance
B8: 5 | C8: Mandsaur | D8: BE NONSENSE | E8: 1232594386 | F8: 46155 | H8: B2C | I8: Shri Yash Mittal | J8: Advance
B9: 6 | C9: Mandsaur | D9: AKSHAY CREDIT COOPERATIVE SOCIETY LIMITED | E9: 1487288297 | F9: 46149 | H9: B2C | I9: Shri Vishal Soni | J9: Advance
B10: 7 | C10: Mandsaur | D10: MERY SLATE PEN WORKS | E10: 1676311014 | F10: 46163 | H10: B2C | I10: Shri Vishal Soni | J10: Advance
B11: 8 | C11: Mandsaur | D11: CENTRAL BANK OF INIDA MANDSAUR BRANCH | E11: 1851294619 | F11: 46163 | H11: B2C | I11: Shri Vishal Soni | J11: BNPL
B12: 9 | C12: Mandsaur | D12: ARHAM TRADING COMPANY | E12: 1499665635 | F12: 46163 | H12: B2C | I12: Shri Yash Mittal | J12: Advance
B13: 10 | C13: Mandsaur | D13: INDIAN OVERSEAS BANK | E13: 1992494624 | F13: 46167 | H13: B2C | I13: Shri Yash Mittal | J13: BNPL
B14: 11 | C14: Mandsaur | D14: PANKAJ PATIDAR | E14: 1126866508 | F14: 46171 | H14: B2C | I14: Shri Yash Mittal | J14: Advance
B15: 12 | C15: Mandsaur | D15: PUNJAB NATIONAL BANK | E15: 1418823332 | F15: 46196 | H15: B2C | I15: Shri Yash Mittal | J15: BNPL
... B86: 83 | C86: Mandsaur | D86: Ajay Kumar Sharma | E86: 1737733673 | F86: 46261 | H86: B2C | I86: Shri Yash Mittal | J86: Advance
B87: 84 | C87: Mandsaur | D87: Babji Trading | E87: 1668644900 | F87: 46266 | H87: B2C | J87: Advance
B88: 85 | C88: Mandsaur | D88: Siya Herbal Product | E88: 1186673833 | F88: 46266 | H88: B2C | J88: Advance
B89: 86 | C89: Mandsaur | D89: BHAGIRATH ORGANICS | E89: 1273897653 | F89: 46266 | H89: B2C | J89: Advance
B90: 87 | C90: Mandsaur | D90: matchline electronics | E90: 1128097368 | F90: 46266 | H90: B2C | J90: Advance
B91: 88 | C91: Mandsaur | D91: Sealwell Neemuch | E91: 1176831301 | F91: 46267 | H91: B2C | J91: Advance
B92: 89 | C92: Mandsaur | D92: Pm shri kendriya vidyalaya crpf Neemuch | E92: 1109730268 | F92: 46268 | H92: B2C | I92: Shri Yash Mittal | J92: BNPL
B93: 90 | C93: Mandsaur | D93: POEMS | E93: 1796374199 | F93: 46276 | H93: B2C | I93: Shri Vishal Soni | J93: Advance
B94: 91 | C94: Mandsaur | D94: SHREE SURBHI DHOOP EVAM VEDLAKSHANA GOMATA KA DESHI GHEE | E94: 1567414215 | F94: 46276 | H94: B2C | J94: Advance
B95: 92 | C95: Mandsaur | D95: GULF TOURS AND TRAVELS | E95: 1753922895 | F95: 46280 | H95: B2C | J95: Advance
B96: 93 | C96: Mandsaur | D96: VIRAT SLATE PENCIL | E96: 1242583964 | F96: 46280 | H96: B2C | I96: Shri Vishal Soni | J96: Advance
B97: 94 | C97: Mandsaur | D97: SHUBHAM SAREE CENTER | E97: 1714059911 | F97: 46280 | H97: B2C | J97: Advance
B98: 95 | C98: Mandsaur | D98: THE GOLD FABRICS | E98: 1722386015 | F98: 46280 | H98: B2C | J98: Advance
B99: 96 | C99: Mandsaur | D99: Shree shyam agro international | E99: 1750186689 | F99: 46282 | H99: B2C | J99: Advance
B100: 97 | C100: Mandsaur | D100: Ajay trading company | E100: 1839454215 | F100: 46284 | H100: B2C | I100: Shri Yash Mittal | J100: Advance
B101: 98 | C101: Mandsaur | D101: SBI Khadawada | E101: 1575445425 | F101: 46286 | H101: B2C | I101: Shri Vishal Soni | J101: BNPL
B102: 99 | C102: Mandsaur | D102: Central Bank of India Shamgarh | E102: 1198278689 | F102: 46286 | H102: B2C | I102: Shri Vishal Soni | J102: BNPL
B103: 100 | C103: Mandsaur | D103: Kanha Collection | E103: 1270346341 | F103: 46286 | H103: B2C | I103: Shri Vishal Soni | J103: Advance
B104: 101 | C104: Mandsaur | D104: Vinod tailor | E104: 1884869881 | F104: 46293 | H104: B2C | I104: Shri Yash Mittal | J104: Advance
B105: 102 | C105: Mandsaur | D105: NEEMUCH SPICES LLP | E105: 1901963132 | F105: 46293 | H105: B2C | I105: Shri Yash Mittal | J105: Advance

Sheet Ratlam
F2: From Date 01.04.2026 to 31.08.2026
B3: S.No. | C3: Division | D3: Name of Customer | E3: Customer ID | F3: Date of Onboarding | G3: Product Type | H3: B2B Or B2C | I3: Name of ME Who Onboarded | J3: Customer Type Advance/ BNPL
B4: 1 | C4: Ratlam | D4: Bank of Baroda jaora branch | E4: 1389789531 | F4: 46205 | G4: Speed Post Document | H4: B2C | I4: Abhishek Malviye | J4: BNPL
B5: 2 | C5: Ratlam | D5: DIVINE FEMME | E5: 1162813943 | F5: 46241 | G5: India Post Parcel Contractual | H5: B2C | I5: Abhishek Malviye | J5: Advance
B6: 3 | C6: Ratlam | D6: Kashi Saree | E6: 1300401626 | F6: 46216 | G6: India Post Parcel Contractual | H6: B2C | I6: Abhishek Malviye | J6: Advance
B7: 4 | C7: Ratlam | D7: Jay Dhakad | E7: 1239000513 | F7: 21.05.2026 | G7: India Post Parcel Contractual | H7: B2C | I7: Abhishek Malviye | J7: Advance
B8: 5 | C8: Ratlam | D8: vithalesh sarees | E8: 1196273906 | F8: 18.08.2026 | G8: India Post Parcel Contractual | H8: B2C | I8: Abhishek Malviye | J8: Advance
B9: 6 | C9: Ratlam | D9: Bank of India Krishi Upaj Mandi | E9: 1693473047 | F9: 04.05.2026 | G9: India Post Parcel Contractual | H9: B2C | I9: Ayush Gupta | J9: Advance
B10: 7 | C10: Ratlam | D10: Rang Varsha Sarees | E10: 1318726462 | F10: 29.05.2026 | G10: India Post Parcel Contractual | H10: B2C | I10: Ayush Gupta | J10: Advance
B11: 8 | C11: Ratlam | D11: SBI Rajwada Chowk | E11: 1170048154 | F11: 46252 | G11: Speed Post Document | H11: B2C | I11: Kavita Bhuriya | J11: BNPL
B12: 9 | C12: Ratlam | D12: HDFC BANK JHABUA BRANCH | E12: 1910649609 | F12: 11.06.2026 | G12: Speed Post Document | H12: B2C | I12: Kavita Bhuriya | J12: BNPL
B13: 10 | C13: Ratlam | D13: Divy Narayan Soni | E13: 1254769708 | F13: 21.05.2026 | G13: Speed Post Parcel Contractual | H13: B2B | I13: Kunal Baurasi | J13: Advance
B14: 11 | C14: Ratlam | D14: PANCHAL HOTELWARE AND MACHINARY Lohar road Ratlam | E14: 1241371047 | F14: 16.07.2026 | G14: India Post Parcel Contractual | H14: B2C | I14: Kunal Baurasi | J14: Advance
B15: 12 | C15: Ratlam | D15: Puneet Enterprises | E15: 1351719501 | F15: 25.04.2026 | G15: India Post Parcel Contractual | H15: B2B | I15: Ayush Gupta | J15: Advance
B16: 13 | C16: Ratlam | D16: Sai Services | E16: 1714557030 | F16: 25.06.2026 | G16: India Post Parcel Contractual | H16: B2C | I16: Kunal Baurasi | J16: Advance
B17: 14 | C17: Ratlam | D17: SINDAL AND COMPANY | E17: 1604629625 | F17: 15.05.2026 | G17: India Post Parcel Contractual | H17: B2C | I17: Kunal Baurasi | J17: Advance
B18: 15 | C18: Ratlam | D18: Arihant Imitation | E18: 1444165342 | F18: 18.08.2026 | G18: India Post Parcel Contractual | H18: B2C | I18: Surendra Singh | J18: Advance
B19: 16 | C19: Ratlam | D19: CHETNA TAILOR | E19: 1630516103 | F19: 29.07.2026 | G19: India Post Parcel Contractual | H19: B2C | I19: Ayush Gupta | J19: Advance
B20: 17 | C20: Ratlam | D20: HARDIK BARMECHA | E20: 1908960328 | F20: 46241 | G20: India Post Parcel Contractual | H20: B2C | I20: Surendra Singh | J20: Advance
B21: 18 | C21: Ratlam | D21: MANMEET SAREES | E21: 1225279034 | F21: 46241 | G21: India Post Parcel Contractual | H21: B2C | I21: Surendra Singh | J21: Advance
B22: 19 | C22: Ratlam | D22: NAKODA NX Ratlam | E22: 1468276742 | F22: 46219 | G22: India Post Parcel Contractual | H22: B2C | I22: Surendra Singh | J22: Advance
B23: 20 | C23: Ratlam | D23: Khabiya Cloth Store | E23: 1000057272 | F23: 21.05.2026 | G23: India Post Parcel Contractual | H23: B2C | I23: Ayush Gupta | J23: Advance
B24: 21 | C24: Ratlam | D24: chirag prodocut | E24: 1254012899 | F24: 46266 | G24: India Post Parcel Contractual | H24: B2C | I24: Ashok Jatiya | J24: Advance
B25: 22 | C25: Ratlam
B26: 23 | C26: Ratlam
B27: 24 | C27: Ratlam
B28: 25 | C28: Ratlam

Sheet Sehore
F2: From Date 01.04.2026 to 31.08.2026
B3: S.No. | C3: Division | D3: Name of Customer | E3: Customer ID | F3: Date of Onboarding | G3: Product Type | H3: B2B Or B2C | I3: Name of ME Who Onboarded | J3: Customer Type Advance/ BNPL
B4: 1 | C4: Sehore | D4: SARTHAK ENTERPRISES | E4: 1131913090 | F4: 10.09.2026 | H4: B2C | I4: HEMANT BAGHEL | J4: Advance
B5: 2 | C5: Sehore | D5: JADUI DHAGE | E5: 1978020115 | F5: 10.09.2026 | H5: B2C | I5: HEMANT BAGHEL | J5: Advance
B6: 3 | C6: Sehore | D6: Union Bank of India | E6: 1634270893 | F6: 03.09.2026 | H6: B2C | I6: DEEPIKA VERMA | J6: BNPL
B7: 4 | C7: Sehore | D7: State Bank of India | E7: 1549258110 | F7: 03.09.2026 | H7: B2C | I7: DEEPIKA VERMA | J7: BNPL
B8: 5 | C8: Sehore | D8: Spare Outlet Krishna Soni | E8: 1840236106 | F8: 02.09.2026 | H8: B2C | I8: NEELESH VERMA | J8: Advance
B9: 6 | C9: Sehore | D9: Amit Raj Singh Kushwah | E9: 1905833890 | F9: 02.09.2026 | H9: B2C | I9: NEELESH VERMA | J9: Advance
B10: 7 | C10: Sehore | D10: Divya Gound | E10: 1353715832 | F10: 17.08.2026 | H10: B2C | I10: NEELESH VERMA | J10: Advance
B11: 8 | C11: Sehore | D11: punam rathore | E11: 1404019518 | F11: 16.08.2026 | H11: B2C | I11: HEMANT BAGHEL | J11: Advance
B12: 9 | C12: Sehore | D12: STATE BANK OF INDIA | E12: 1811627323 | F12: 25.08.2026 | H12: B2C | I12: NEELESH VERMA | J12: BNPL
B13: 10 | C13: Sehore | D13: Shree Ji Collection | E13: 1357785958 | F13: 19.08.2026 | H13: B2C | I13: NEELESH VERMA | J13: Advance
B14: 11 | C14: Sehore | D14: Ashu Collection | E14: 1605992803 | F14: 19.08.2026 | H14: B2C | I14: NEELESH VERMA | J14: Advance
B15: 12 | C15: Sehore | D15: Shivna Prakashan | E15: 1662698556 | F15: 14.08.2026 | H15: B2C | I15: HEMANT BAGHEL | J15: Advance
... B59: 56 | C59: Sehore | D59: nayanthara showroom | E59: 1436142823 | F59: 29.09.2026 | H59: B2C | I59: Rajendra pushpad | J59: Advance

Sheet Sheet11

Sheet Ujjain
F2: From Date 01.04.2026 to 31.08.2026
B3: S.No. | C3: Division | D3: Name of Customer | E3: Customer ID | F3: Date of Onboarding | G3: Product Type | H3: B2B Or B2C | I3: Name of ME Who Onboarded | J3: Customer Type Advance/ BNPL
B4: 1 | C4: Ujjain | D4: shakha prabandhak union bank of india | E4: 1841104004 | F4: 46111 | G4: bnpl-speed post | H4: B2C | I4: Anil kumar kayasth
B5: 2 | C5: Ujjain | D5: Shakha prabandhak mohday bhartiy state bankn agar | E5: 1634558796 | F5: 46118 | G5: bnpl-speed post | H5: B2C | I5: Anil kumar kayasth
B6: 3 | C6: Ujjain | D6: Bal krishna veshnav jay jagnant courier | E6: 1715418519 | F6: 46163 | G6: advance customer | H6: B2C | I6: Anil kumar kayasth
B7: 4 | C7: Ujjain | D7: shakha prabandhak mohday kenra bank agar | E7: 1413997724 | F7: 46163 | G7: bnpl-speed post | H7: B2C | I7: Anil kumar kayasth
B8: 5 | C8: Ujjain | D8: shakha prabandhak idbi bank kota road agar | E8: 1932597043 | F8: 46168 | G8: bnpl-speed post | H8: B2C | I8: Anil kumar kayasth
B9: 6 | C9: Ujjain | D9: Principal mohday kendriy vidhyalay agar | E9: 1762876916 | F9: 46181 | G9: bnpl-speed post | H9: B2C | I9: Anil kumar kayasth
B10: 7 | C10: Ujjain | D10: Principal politachnical college ujjain road agar | E10: 1250783523 | F10: 46202 | G10: bnpl-speed post | H10: B2C | I10: Anil kumar kayasth
B11: 8 | C11: Ujjain | D11: Shakha prabandhak bank of india soyatkalan | E11: 1100308643 | F11: 46233 | G11: bnpl-speed post | H11: B2C | I11: Anil kumar kayasth
B12: 9 | C12: Ujjain | D12: Shakha prabandhak bhartiya state bank soyatkalan | E12: 1982377158 | F12: 46233 | G12: bnpl-speed post | H12: B2C | I12: Anil kumar kayasth
B13: 10 | C13: Ujjain | D13: Shakha prabandhak bhartiya state bank barode | E13: 1866594362 | F13: 46233 | G13: bnpl-speed post | H13: B2C | I13: Anil kumar kayasth
B14: 11 | C14: Ujjain | D14: Shakha prabandhak bank of india barode | E14: 1959590361 | F14: 46233 | G14: bnpl-speed post | H14: B2C | I14: Anil kumar kayasth
B15: 12 | C15: Ujjain | D15: STATE BANK OF INDIA MAKSI | E15: 1566212097 | F15: 46121 | G15: BNPL speed post | H15: B2C | I15: DURGA SHANKAR GARASIYA
... B26: 23 | C26: Ujjain | D26: INDIAN OVERSEAS BANK | E26: 1285666740 | F26: 46276 | G26: BNPL SPEED | H26: B2C | I26: DURGA SHANKAR GARASIYA
B27: 24 | C27: Ujjain | D27: SHRIJI VASTRALAYA TARANA | E27: 1319447119 | G27: parcel contractual | H27: B2C | I27: DURGA SHANKAR GARASIYA
B28: 25 | C28: Ujjain | D28: RADHIKA SAREE TARANA | E28: 1371033742 | F28: 46239 | G28: parcel contractual | H28: B2C | I28: DURGA SHANKAR GARASIYA
B29: 26 | C29: Ujjain | D29: RADHIKA SAREE MAKSI | E29: 1435967697 | F29: 46247 | G29: parcel contractual | H29: B2C | I29: DURGA SHANKAR GARASIYA
B30: 27 | C30: Ujjain | D30: PAAMAS HL BAL PVT LTD | E30: 1332607573 | F30: 46281 | G30: parcel contractual | H30: B2C | I30: DURGA SHANKAR GARASIYA
B31: 28 | C31: Ujjain | D31: SARTHAK PURFUME SHAJAPUR | E31: 1478845372 | F31: 46256 | G31: parcel contractual | H31: B2C | I31: DURGA SHANKAR GARASIYA
B32: 29 | C32: Ujjain | D32: GETSABACUS SHUJALPUR | E32: 1376577863 | F32: 16.07.26 | G32: ADVANCED CUSTOMER | H32: B2C | I32: HARSHIT PARMAR
B33: 30 | C33: Ujjain | D33: DIWAN SINGH RAJPUT | E33: 1676139920 | F33: 20.07.26 | G33: ADVANCED CUSTOMER | H33: B2C | I33: HARSHIT PARMAR
B34: 31 | C34: Ujjain | D34: SBI POLAI KALAN | E34: 1659474901 | F34: 03.08.26 | G34: BNPL | H34: B2C | I34: HARSHIT PARMAR
B35: 32 | C35: Ujjain | D35: THE GOLDEN STRAW SALSALAI | E35: 1641489596 | F35: 08.08.26 | G35: ADVANCED CUSTOMER | H35: B2C | I35: HARSHIT PARMAR
B36: 33 | C36: Ujjain | D36: BANK OF INDIA SHUJALPUR | E36: 1489575716 | F36: 14.08.26 | G36: BNPL | H36: B2C | I36: HARSHIT PARMAR
B37: 34 | C37: Ujjain | D37: MANISH VISHWAKARMA, SHUJALPUR | E37: 1351269580 | F37: 21.08.26 | G37: ADVANCED CUSTOMER | H37: B2C | I37: HARSHIT PARMAR
B38: 35 | C38: Ujjain | D38: Virendra pa | E38: 1142829004 | F38: 46134 | G38: ADVANCED CUSTOMER | H38: B2C | I38: RAHUL AGRAWAL
B39: 36 | C39: Ujjain | D39: jay makwana | E39: 1186471925 | F39: 46133 | G39: ADVANCED CUSTOMER | H39: B2C | I39: RAHUL AGRAWAL
B40: 37 | C40: Ujjain | D40: Divyanshu Khatri | E40: 1966278010 | F40: 46127 | G40: ADVANCED CUSTOMER | H40: B2C | I40: RAHUL AGRAWAL
B41: 38 | C41: Ujjain | D41: SHRI COLLECTION Customer ID:: | E41: 1869951677 | F41: 46125 | G41: ADVANCED CUSTOMER | H41: B2C | I41: RAHUL AGRAWAL
B42: 39 | C42: Ujjain | D42: MOHIT SINGH PANWAR | E42: 1132441153 | F42: 46123 | G42: ADVANCED CUSTOMER | H42: B2C | I42: RAHUL AGRAWAL
B43: 40 | C43: Ujjain | D43: ANIKET AGRAWAL | E43: 1307425262 | F43: 46122 | G43: ADVANCED CUSTOMER | H43: B2C | I43: RAHUL AGRAWAL
B44: 41 | C44: Ujjain | D44: KUNWAR SA WEDDING STORE | E44: 1663820107 | F44: 46121 | G44: ADVANCED CUSTOMER | H44: B2C | I44: RAHUL AGRAWAL
B45: 42 | C45: Ujjain | D45: TANA BANA BOUTIQUE | E45: 1988426117 | F45: 46114 | G45: ADVANCED CUSTOMER | H45: B2C | I45: RAHUL AGRAWAL
B46: 43 | C46: Ujjain | D46: DESIALCHEMIST | E46: 1623792749 | F46: 46156 | G46: ADVANCED CUSTOMER | H46: B2C | I46: RAHUL AGRAWAL
B47: 44 | C47: Ujjain | D47: PARWATI HANDLOOM | E47: 1391029143 | F47: 46191 | G47: ADVANCED CUSTOMER | H47: B2C | I47: RAHUL AGRAWAL
B48: 45 | C48: Ujjain | D48: KAMAL PATIDAR | E48: 1383939345 | F48: 46232 | G48: ADVANCED CUSTOMER | H48: B2C | I48: RAHUL AGRAWAL
B49: 46 | C49: Ujjain | D49: ROOP SHREE FASHION | E49: 1162813223 | F49: 46230 | G49: ADVANCED CUSTOMER | H49: B2C | I49: RAHUL AGRAWAL
... B63: 60 | C63: Ujjain | D63: SIXTH SENSE MARKETING PVT LTD | E63: 1431176158 | F63: 46238 | G63: ADVANCED CUSTOMER | H63: B2C | I63: RAHUL AGRAWAL
B64: 61 | C64: Ujjain | D64: Burhanuuddin Bagwala | E64: 1541440822 | F64: AUGUST | G64: ADVANCED CUSTOMER | H64: B2C | I64: RAHUL AGRAWAL
B65: 62 | C65: Ujjain | D65: GAGAN YOGI | E65: 1601641926 | F65: AUGUST | G65: ADVANCED CUSTOMER | H65: B2C | I65: RAHUL AGRAWAL
B66: 63 | C66: Ujjain | D66: ayurved panchkaram centre | E66: 1940520225 | F66: AUGUST | G66: ADVANCED CUSTOMER | H66: B2C | I66: RAHUL AGRAWAL
B67: 64 | C67: Ujjain | D67: mohit goyal | E67: 1174589213 | F67: AUGUST | G67: ADVANCED CUSTOMER | H67: B2C | I67: RAHUL AGRAWAL
B68: 65 | C68: Ujjain | D68: VINOD PORWAL | E68: 1971673186 | F68: AUGUST | G68: ADVANCED CUSTOMER | H68: B2C | I68: RAHUL AGRAWAL
B69: 66 | C69: Ujjain | D69: Gauv aadi shakti Private limited | E69: 1430224002 | F69: AUGUST | G69: ADVANCED CUSTOMER | H69: B2C | I69: RAHUL AGRAWAL
B70: 67 | C70: Ujjain | D70: International society for Krishna consciousness | E70: 1247495565 | F70: AUGUST | G70: ADVANCED CUSTOMER | H70: B2C | I70: RAHUL AGRAWAL
B71: 68 | C71: Ujjain | D71: JODHPUR RAJWADI COLLECTION | E71: 1335749271 | F71: AUGUST | G71: ADVANCED CUSTOMER | H71: B2C | I71: RAHUL AGRAWAL
B72: 69 | C72: Ujjain | D72: PRIT UNDER GARMENTS | E72: 1708800018 | F72: AUGUST | G72: ADVANCED CUSTOMER | H72: B2C | I72: RAHUL AGRAWAL
B73: 70 | C73: Ujjain | D73: KAMAL PATIDAR | E73: 1383939345 | F73: AUGUST | G73: ADVANCED CUSTOMER | H73: B2C | I73: RAHUL AGRAWAL
B74: 71 | C74: Ujjain | D74: VINOD KHABIYA | E74: 1479992063 | F74: AUGUST | G74: ADVANCED CUSTOMER | H74: B2C | I74: RAHUL AGRAWAL
B75: 72 | C75: Ujjain | D75: KIRTI AKODIYA | E75: 1571949494 | F75: AUGUST | G75: ADVANCED CUSTOMER | H75: B2C | I75: RAHUL AGRAWAL
... B80: 77 | C80: Ujjain | D80: CHERRY CLOSET | E80: 1983629855 | F80: AUGUST | G80: ADVANCED CUSTOMER | H80: B2C | I80: RAHUL AGRAWAL
B81: 78 | C81: Ujjain | D81: Sewa Satkaar | E81: 1766101758 | F81: 46134 | G81: ADVANCED CUSTOMER | H81: B2C | I81: RISHABH SINGH GOUR
B82: 79 | C82: Ujjain | D82: Annapurna collection | E82: 1425746086 | F82: 46128 | G82: ADVANCED CUSTOMER | H82: B2C | I82: RISHABH SINGH GOUR
B83: 80 | C83: Ujjain | D83: Artnaturale | E83: 1475000755 | F83: 46127 | G83: ADVANCED CUSTOMER | H83: B2C | I83: RISHABH SINGH GOUR
B84: 81 | C84: Ujjain | D84: BLACK HOUSE | E84: 1735010775 | F84: 46113 | G84: ADVANCED CUSTOMER | H84: B2C | I84: RISHABH SINGH GOUR
B85: 82 | C85: Ujjain | D85: Aishwarya Dubey | E85: 1343360453 | F85: 46167 | G85: ADVANCED CUSTOMER | H85: B2C | I85: RISHABH SINGH GOUR
B86: 83 | C86: Ujjain | D86: India phosphate and allied industries Private limited | E86: 1167924079 | F86: 46164 | G86: ADVANCED CUSTOMER | H86: B2C | I86: RISHABH SINGH GOUR
B87: 84 | C87: Ujjain | D87: Your Fashion Store | E87: 1158709634 | F87: 46154 | G87: ADVANCED CUSTOMER | H87: B2C | I87: RISHABH SINGH GOUR
B88: 85 | C88: Ujjain | D88: Dr Yogesh Patidar | E88: 1661377226 | F88: 46153 | G88: ADVANCED CUSTOMER | H88: B2C | I88: RISHABH SINGH GOUR
B89: 86 | C89: Ujjain | D89: Sansa Healthcare | E89: 1726288359 | F89: 46185 | G89: ADVANCED CUSTOMER | H89: B2C | I89: RISHABH SINGH GOUR
B90: 87 | C90: Ujjain | D90: AYAN PATEL | E90: 1144656423 | F90: 46227 | G90: ADVANCED CUSTOMER | H90: B2C | I90: RISHABH SINGH GOUR
B91: 88 | C91: Ujjain | D91: SHREE HORI METALS | E91: 1881759554 | F91: 46225 | G91: ADVANCED CUSTOMER | H91: B2C | I91: RISHABH SINGH GOUR
B92: 89 | C92: Ujjain | D92: Mayank Parmar | E92: 1132703381 | F92: 46211 | G92: ADVANCED CUSTOMER | H92: B2C | I92: RISHABH SINGH GOUR
... B95: 92 | C95: Ujjain | D95: SMELL KILL | E95: 1939800132 | F95: 46254 | G95: ADVANCED CUSTOMER | H95: B2C | I95: RISHABH SINGH GOUR
B96: 93 | C96: Ujjain | D96: Seva Satkar | E96: 1766101758 | F96: AUGUST | G96: ADVANCED CUSTOMER | H96: B2C | I96: RISHABH SINGH GOUR
B97: 94 | C97: Ujjain | D97: Digvijay Parashar | E97: 1501610967 | F97: AUGUST | G97: ADVANCED CUSTOMER | H97: B2C | I97: RISHABH SINGH GOUR
B98: 95 | C98: Ujjain | D98: Abhishek Sharma | E98: 1240786559 | F98: AUGUST | G98: ADVANCED CUSTOMER | H98: B2C | I98: RISHABH SINGH GOUR
B99: 96 | C99: Ujjain | D99: Abhiksha The Saree Queen | E99: 1239332811 | F99: AUGUST | G99: ADVANCED CUSTOMER | H99: B2C | I99: RISHABH SINGH GOUR
B100: 97 | C100: Ujjain | D100: Sansa Healthcare | E100: 1726288359 | F100: AUGUST | G100: ADVANCED CUSTOMER | H100: B2C | I100: RISHABH SINGH GOUR
B101: 98 | C101: Ujjain | D101: Aishwarya Dubey | E101: 1343360453 | F101: AUGUST | G101: ADVANCED CUSTOMER | H101: B2C | I101: RISHABH SINGH GOUR
B102: 99 | C102: Ujjain | D102: Annapurna collection | E102: 1425746086 | F102: AUGUST | G102: ADVANCED CUSTOMER | H102: B2C | I102: RISHABH SINGH GOUR
B103: 100 | C103: Ujjain | D103: ABHIJEET SINGH PANWAR MAHENDRA JI | E103: 1907228011 | F103: AUGUST | G103: ADVANCED CUSTOMER | H103: B2C | I103: RISHABH SINGH GOUR
B104: 101 | C104: Ujjain | D104: MONISHKA TIWARI | E104: 1780666446 | F104: AUGUST | G104: ADVANCED CUSTOMER | H104: B2C | I104: RISHABH SINGH GOUR
B105: 102 | C105: Ujjain | D105: MUMTAZ BATIK | E105: 1107368498 | F105: AUGUST | G105: ADVANCED CUSTOMER | H105: B2C | I105: RISHABH SINGH GOUR

Sheet RMS ID Dn
F2: From Date 01.04.2026 to 31.09.2026
B3: S.No. | C3: Division | D3: Name of Customer | E3: Customer ID | F3: Date of Onboarding | G3: Product Type | H3: B2B Or B2C | I3: Name of ME Who Onboarded | J3: Customer Type Advance/ BNPL
B4: 1 | C4: RMS ID Dn | D4: ALL MAHARASHTRA LAW REPORTER | E4: 1525023132 | F4: 46083 | G4: Magazine Post | H4: B2C | I4: Narendra Baviskar | J4: Advance
B5: 2 | C5: RMS ID Dn | D5: Income Tax judgements | E5: 1510618050 | F5: 46087 | G5: Magazine Post | H5: B2C | I5: Narendra Baviskar | J5: Advance
B6: 3 | C6: RMS ID Dn | D6: lucky xerox | E6: 1511219040 | F6: 46087 | G6: Indiapost Parcel Contractual | H6: B2C | I6: Narendra Baviskar | J6: Advance
B7: 4 | C7: RMS ID Dn | D7: jion media publications | E7: 1528883544 | F7: 46098 | G7: Magazine Post | H7: B2C | I7: Narendra Baviskar | J7: Advance
B8: 5 | C8: RMS ID Dn | D8: SATYADHI SHARMA CLASSES | E8: 1982335310 | F8: 46101 | G8: Indiapost Parcel Contractual | H8: B2C | I8: Narendra Baviskar | J8: Advance
B9: 6 | C9: RMS ID Dn | D9: SHREE KALOTA PATEL PUSHP | E9: 1612261697 | F9: 46142 | G9: Magazine Post | H9: B2C | I9: Narendra Baviskar | J9: Advance
B10: 7 | C10: RMS ID Dn | D10: NIRMAN IAS | E10: 3000070094 | F10: 46150 | G10: Registered Mails | H10: B2C | I10: Narendra Baviskar | J10: Advance
B11: 8 | C11: RMS ID Dn | D11: Eye gear optics india private limited | E11: 1721126209 | F11: 46156 | G11: Registered Mails | H11: B2C | I11: Narendra Baviskar | J11: Advance
B12: 9 | C12: RMS ID Dn | D12: AKSHAY ENGINEERING | E12: 1597110634 | F12: 46161 | G12: Registered Mails | H12: B2C | I12: Narendra Baviskar | J12: Advance
B13: 10 | C13: RMS ID Dn | D13: DELIGHTS ELECTRICALS PRIVATE LIMITED | E13: 1636228640 | F13: 46161 | G13: Speed Post ParcelÂ Domestic | H13: B2C | I13: Narendra Baviskar | J13: Advance
B14: 11 | C14: RMS ID Dn | D14: TAX LAW DECISIONS | E14: 1566240524 | F14: 46164 | G14: Magazine Post | H14: B2C | I14: Narendra Baviskar | J14: Advance
B15: 12 | C15: RMS ID Dn | D15: GYAN PUBLICATIN | E15: 1584356202 | F15: 46167 | G15: Magazine Post | H15: B2C | I15: Narendra Baviskar | J15: Advance
... B43: 40 | C43: RMS ID Dn | D43: AAKASH TREDARS | E43: 1827455456 | F43: 46265 | G43: Indiapost Parcel Contractual | H43: B2C | I43: Narendra Baviskar | J43: Advance
B44: 41 | C44: RMS ID Dn | D44: KANKAMAL SANGHVI PARMARTHIK TRUST | E44: 1868160470 | F44: 02.09.2026 | G44: Indiapost Parcel Contractual | H44: B2C | I44: Narendra Baviskar | J44: Advance
B45: 42 | C45: RMS ID Dn | D45: THE ACADEMICIAN | E45: 1480067875 | F45: 05.09.2026 | G45: Magazine Post | H45: B2C | I45: Narendra Baviskar | J45: Advance
B46: 43 | C46: RMS ID Dn | D46: FAKRUDDIN LUKMANI | E46: 1967768859 | F46: 08.09.2026 | G46: Speed Post | H46: B2C | I46: Narendra Baviskar | J46: Advance
B47: 44 | C47: RMS ID Dn | D47: SHRI DIGAMBER JAIN YUVAK SANGH | E47: 1701347064 | F47: 11.09.2026 | G47: Indiapost Parcel Contractual | H47: B2C | I47: Narendra Baviskar | J47: Advance
B48: 45 | C48: RMS ID Dn | D48: GAMBHIR ENTERPRISES | E48: 1803276809 | F48: 17.09.2026 | G48: Speed Post,Indiapost Parcel Contractual | H48: B2C | I48: Narendra Baviskar | J48: Advance
B49: 46 | C49: RMS ID Dn | D49: RUHI BANO W/O JAHID KHAN | E49: 1673674046 | F49: 21.09.2026 | G49: Indiapost Parcel Contractual | H49: B2C | I49: Narendra Baviskar | J49: Advance
B50: 47 | C50: RMS ID Dn | D50: JMD ENTERPRISES | E50: 1255909570 | F50: 25.09.2026 | G50: Indiapost Parcel Contractual | H50: B2C | I50: Narendra Baviskar | J50: Advance
B51: 48 | C51: RMS ID Dn | D51: NEW ANMOL COSMETICS | E51: 1279430186 | F51: 26.09.2026 | G51: Indiapost Parcel Contractual | H51: B2C | I51: Narendra Baviskar | J51: Advance
B52: 49 | C52: RMS ID Dn | D52: BIYANI INDUSTRIAL TEXTILES PVT .LTD | E52: 1683888422 | F52: 26.09.2026 | G52: Speed Post | H52: B2C | I52: Narendra Baviskar | J52: Advance
B53: 50 | C53: RMS ID Dn | D53: ORIGIN EXPRESS SERVICES | E53: 1296899413 | F53: 28.09.2026 | G53: Speed Post | H53: B2C | I53: Narendra Baviskar | J53: Advance
B54: 51 | C54: RMS ID Dn | D54: D B M S & Co | E54: 1625383718 | F54: 28.09.2026 | G54: Speed Post | H54: B2C | I54: Narendra Baviskar | J54: Advance
B55: 52 | C55: RMS ID Dn | D55: M/S 3G AQUA WATER TREATMENT TECHNOLOGY | E55: 1961703594 | F55: 28.09.2026 | G55: Speed Post | H55: B2C | I55: Narendra Baviskar | J55: Advance
B56: 53 | C56: RMS ID Dn | D56: SKASHI JETHANI | E56: 1561115828 | F56: 29.09.2026 | G56: Indiapost Parcel Contractual | H56: B2C | I56: Narendra Baviskar | J56: Advance

Sheet Sheet12
